TAREA2/cmos_version/tester.v
// Tester oficial para la sintetización tanto rtlil como la mapeada a la biblioteca

module tester(
clk,             // Entrada de reloj
reset,         // Entrada de reset
sensor_entrance, // Sensor de entrada
sensor_exit,     // Sensor de salida
input_password,  // Contraseña ingresada de 8 bits
gate_open,      // Salida de compuerta abierta
alarm_wrong_pin,// Salida de alarma de contraseña incorrecta
gate_close,     // Salida de compuerta de compuerta cerrada
alarm_block     
);

output clk, reset, sensor_entrance, sensor_exit; // Las salidas de este módulo son las entradas que le llegarán al controlador
output [7:0] input_password;
input gate_open, alarm_wrong_pin, gate_close, alarm_block;


wire gate_open, alarm_wrong_pin, gate_close, alarm_block; // Se establecen los cables
reg clk, reset, sensor_entrance, sensor_exit;
reg [7:0] input_password;

initial begin  // Inicializamos las señales de entrada en 0
    clk = 0;
    reset = 0;
    sensor_entrance = 0;
    sensor_exit = 0;
    #5 reset = 1;
    #10 reset = 0;

    //Prueba #1: Funcionamiento normal básico
    $display("Prueba #1: Funcionamiento normal básico");
    #10 sensor_entrance = 1; // Llegada de vehículo 
    #10 input_password = 8'b01001001; // Ingresa contraseña correcta
    $display("Esperando que la compuerta se abra...");
    #10 sensor_entrance = 0; // Sensor en bajo ya que está terminando de ingresar un vehículo
    #10 sensor_exit = 1; // Sensor de que ya el vehículo ingresó
    $display("Esperando que la compuerta se cierre...");
    #10 sensor_exit = 0;
   
    
    // Prueba #2: Ingreso de PIN incorrecto menos de 3 veces
    $display("Prueba #2: Ingreso de PIN incorrecto menos de 3 veces");
    #20 sensor_entrance = 1; // Llegada de vehículo
    $display("Esperando contraseña...");
    #10 input_password = 8'b10101010; // Ingreso de primer pin incorrecto
    $display("Esperando contraseña...");
    #10 input_password = 8'b11101100; // Ingreso de segundo pin incorrecto
    $display("Esperando contraseña...");
    #10 input_password = 8'b01001001; // Ingreso de pin correcto
    // Esperar a que la compuerta se abra 01001001
    $display("Esperando que la compuerta se abra...");
    #10 sensor_entrance = 0; // Sensor en bajo
    #10 sensor_exit =1;
    // Esperar a que la compuerta se cierre
    $display("Esperando que la compuerta se cierre...");
    #10 sensor_exit = 0;
   
    // Prueba #3: Ingreso de pin incorrecto 3 veces
    $display("Prueba #3: Ingreso de pin incorrecto 3 veces");
    #10 sensor_entrance = 1; // Llegada de vehículo
    #10 input_password = 8'b10101010; // Ingreso de primer pin incorrecto
    #10 input_password = 8'b11001100; // Ingreso de segundo pin incorrecto
    #10 input_password = 8'b11110000; // Ingreso de tercer pin incorrecto
    #20 input_password = 8'b01001001; // Ingresa contraseña correcta
    $display("Esperando que la compuerta se abra...");
    #10 sensor_entrance = 0; // Sensor en bajo ya que está terminando de ingresar un vehículo
    #10 sensor_exit = 1; // Sensor de que ya el vehículo ingresó
    $display("Esperando que la compuerta se cierre...");
    #10 sensor_exit = 0;
  
    //Prueba #4  
    $display("Prueba #4: alarma de bloqueo"); 
    #10 sensor_exit = 1;
    #10 sensor_entrance = 1; // Llegada de vehículo
    #10 input_password = 8'b10101010; // Ingreso de pin incorrecto
    #10 input_password = 8'b11001100; // Ingreso de pin incorrecto
    #10 input_password = 8'b01001001; // Ingresa contraseña correcta
    $display("Esperando que la compuerta se abra...");
    #10 sensor_entrance = 0; // Sensor en bajo
    #10 sensor_exit = 1; // Sensor de que ya el vehículo ingresó
    $display("Esperando que la compuerta se cierre...");
    #10 sensor_exit = 0;
    #400 $finish; // Termina la simulación
end

always #5 clk = ~clk; // clk cada 5 unidades de tiempo
endmodule

TAREA2/cmos_version/controller.v
module controller( 
 clk,                    // Se establecen las señales del módulo
 reset,
 sensor_entrance, 
 sensor_exit, 
 input_password,
 gate_open,
 gate_close,
 alarm_wrong_pin,
 alarm_block
    );


input clk, reset, sensor_entrance, sensor_exit; // Se indican las entradas del módulo
input [7:0] input_password;
output reg gate_open, alarm_wrong_pin, gate_close, alarm_block; // Se indican las salidas del módulo

reg [2:0] current_state;
reg [2:0] count0;

reg [2:0] nxt_state;
reg [2:0] nxt_count0;           

parameter CORRECT_PASSWORD = 8'b01001001; // Parámetro de la contraseña correcta para ser comparada internamente
parameter MAX_ATTEMPTS = 3; // Valor máximo de intentos de ingreso de pin
//Ambas variables almacenadas en registros hechos con FF de flanco positivo.
// Un FF por bit de cada variable.
           
always @(posedge clk) begin
  if (reset) begin
    current_state  <= 3'b000;
    count0 <= 3'b000; 
  end else begin
    current_state  <= nxt_state;
    count0 <= nxt_count0;
  end
end  //Fin de los flip flops

always @(*) begin

// Valores por defecto

  nxt_state = current_state;   //Para completar el comportamiento del FF se necesita
                       //que por defecto el nxt_state sostenga el valor del estado
                       //anterior
  nxt_count0 = count0; // Igual al caso de state y nxt_state, para garantizar el 
                       // comportamiento del FF. 
   
  gate_open = 1'b0; 
  gate_close = 1'b0; 
  alarm_block = 1'b0; 
  alarm_wrong_pin = 1'b0; 
  
// Comportamiento de la máquina de estados
// Define las transiciones de próximo estado según el diagrama ASM
// visto en clase y el comportamiento de "valid" y "count0" en el 
// último estado, según la especificación.

  case(current_state)
    3'b000: begin
    		gate_close = 1'b1;
    		if (sensor_entrance) nxt_state = 3'b001;
		if (sensor_exit && sensor_entrance) nxt_state = 3'b011;
		//nxt_state = 3'b000;
	    end
   
    3'b001: begin
        	gate_close = 1'b1;
        	//if (sensor_exit && sensor_entrance) nxt_state = 3'b011; 
        	if (input_password == CORRECT_PASSWORD) begin
            		nxt_state = 3'b010;
        	end
        	else if (input_password != CORRECT_PASSWORD && nxt_count0 < MAX_ATTEMPTS) begin
            		nxt_count0 = count0 + 1;
            		nxt_state = 3'b001;
        	end
        	else if (input_password != CORRECT_PASSWORD && nxt_count0 >= MAX_ATTEMPTS) begin
            		alarm_wrong_pin = 1'b1;
            		nxt_count0 = 3'b000;
            		nxt_state = 3'b001;
            		end
            	//nxt_state = 3'b001;
            		
    end                                       
    3'b010: begin 
    		gate_open = 1'b1;
    		nxt_count0 = 3'b000;
    		// nxt_state = 3'b000;
    	      	if (sensor_exit) nxt_state = 3'b000; //HACER PRUEBA AHORITA
    	    end
    
    3'b011: begin
    gate_close = 1'b1;
    alarm_block = 1'b1;
    
    if (input_password != CORRECT_PASSWORD && nxt_count0 < MAX_ATTEMPTS) begin
        nxt_count0 = count0 + 1;
        nxt_state = 3'b011;
    end
    else if (input_password == CORRECT_PASSWORD) begin
        nxt_state = 3'b010;
    end
end

               
    
    default:   nxt_state = 3'b000; // Si la máquina entrara en un estado inesperado, regrese al inicio.
  endcase

end // Este end corresponde al always @(*) de la lógica combinacional

endmodule

TAREA2/conductual_version/testbench.v
`include "tester.v"
`include "controller.v"

module controller_tb;
wire clk;                  //Aquí se establecen los cables de las entradas y las salidas del sistema
wire reset;
wire sensor_entrance;
wire sensor_exit;
wire [7:0] input_password;
wire gate_open;
wire alarm_wrong_pin;
wire gate_close;
wire alarm_block;

initial begin
	$dumpfile("resultados.vcd"); // Se generan los resultados para poder verlos con gtkwave
	$dumpvars(-1, U0);
	$monitor ("sensor_entrance=%b,sensor_exit=%b,gate_open=%b,gate_close=%b,alarm_pin=%b, alarm_block=%b", sensor_entrance, sensor_exit, gate_open, gate_close, alarm_wrong_pin, alarm_block); // Se despliega en consola el funcionamiento del sistema
  end
// Instanciar el controlador
controller U0 (
    .clk(clk),
    .reset(reset),
    .sensor_entrance(sensor_entrance),
    .sensor_exit(sensor_exit),
    .input_password(input_password),
    .gate_open(gate_open),
    .alarm_wrong_pin(alarm_wrong_pin),
    .gate_close(gate_close),
    .alarm_block(alarm_block)
);

// Instanciar el probador
tester P0 (
    .clk(clk),
    .reset(reset),
    .sensor_entrance(sensor_entrance),
    .sensor_exit(sensor_exit),
    .input_password(input_password),
    .gate_open(gate_open),
    .alarm_wrong_pin(alarm_wrong_pin),
    .gate_close(gate_close),
    .alarm_block(alarm_block)
);

endmodule

TAREA2/conductual_version/resultados.vcd
$date
	Fri May  3 22:16:44 2024
$end
$version
	Icarus Verilog
$end
$timescale
	1s
$end
$scope module controller_tb $end
$scope module U0 $end
$var wire 1 ! clk $end
$var wire 8 " input_password [7:0] $end
$var wire 1 # reset $end
$var wire 1 $ sensor_entrance $end
$var wire 1 % sensor_exit $end
$var reg 1 & alarm_block $end
$var reg 1 ' alarm_wrong_pin $end
$var reg 3 ( count0 [2:0] $end
$var reg 3 ) current_state [2:0] $end
$var reg 1 * gate_close $end
$var reg 1 + gate_open $end
$var reg 3 , nxt_count0 [2:0] $end
$var reg 3 - nxt_state [2:0] $end
$upscope $end
$upscope $end
$enddefinitions $end
#0
$dumpvars
b0 -
bx ,
0+
0*
bx )
bx (
0'
0&
0%
0$
0#
bx "
0!
$end
#5
1*
b0 ,
b0 (
b0 )
1!
1#
#10
0!
#15
1!
0#
#20
0!
#25
b1 )
b1 -
1*
1!
1$
#30
0!
#35
1+
b10 )
b10 -
0*
1!
b1001001 "
#40
0!
#45
1+
1!
0$
#50
0!
#55
1*
b0 )
b0 -
0+
1!
1%
#60
0!
#65
1*
1!
0%
#70
0!
#75
1!
#80
0!
#85
b1 )
b10 -
1*
1!
1$
#90
0!
#95
b1 (
b10 ,
1*
b1 -
1!
b10101010 "
#100
0!
#105
b10 (
1*
b11 ,
1!
b11101100 "
#110
0!
#115
1+
b10 )
b10 -
0*
b0 ,
1!
b1001001 "
#120
0!
#125
b0 (
1+
b0 ,
1!
0$
#130
0!
#135
1*
b0 )
b0 -
0+
1!
1%
#140
0!
#145
1*
1!
0%
#150
0!
#155
b1 )
b10 -
1*
1!
1$
#160
0!
#165
b1 (
b10 ,
1*
b1 -
1!
b10101010 "
#170
0!
#175
b10 (
1*
b11 ,
1!
b11001100 "
#180
0!
#185
1'
b11 (
1*
b0 ,
1!
b11110000 "
#190
0!
#195
b1 ,
0'
1*
b0 (
1!
#200
0!
#205
1+
b10 )
b10 -
0*
b0 ,
1!
b1001001 "
#210
0!
#215
1+
1!
0$
#220
0!
#225
1*
b0 )
b0 -
0+
1!
1%
#230
0!
#235
1*
1!
0%
#240
0!
#245
1*
1!
1%
#250
0!
#255
1&
b11 )
b10 -
1*
1!
1$
#260
0!
#265
b1 (
b10 ,
1&
1*
b11 -
1!
b10101010 "
#270
0!
#275
b10 (
1&
1*
b11 ,
1!
b11001100 "
#280
0!
#285
1+
b10 )
b0 -
0&
0*
b0 ,
1!
b1001001 "
#290
0!
#295
1*
b0 (
b0 )
0+
b0 ,
b0 -
1!
0$
#300
0!
#305
1!
#310
0!
#315
1*
1!
0%
