TAREA2/retardos/tester.v
// Tester oficial para la sintetización tanto rtlil como la mapeada a la biblioteca

module tester(
clk,             // Entrada de reloj
reset,         // Entrada de reset
sensor_entrance, // Sensor de entrada
sensor_exit,     // Sensor de salida
input_password,  // Contraseña ingresada de 8 bits
gate_open,      // Salida de compuerta abierta
alarm_wrong_pin,// Salida de alarma de contraseña incorrecta
gate_close,     // Salida de compuerta de compuerta cerrada
alarm_block     
);

output clk, reset, sensor_entrance, sensor_exit; // Las salidas de este módulo son las entradas que le llegarán al controlador
output [7:0] input_password;
input gate_open, alarm_wrong_pin, gate_close, alarm_block;


wire gate_open, alarm_wrong_pin, gate_close, alarm_block; // Se establecen los cables
reg clk, reset, sensor_entrance, sensor_exit;
reg [7:0] input_password;

initial begin  // Inicializamos las señales de entrada en 0
    clk = 0;
    reset = 0;
    sensor_entrance = 0;
    sensor_exit = 0;
    #10 reset = 1;
    #20 reset = 0;

    //Prueba #1: Funcionamiento normal básico
    $display("Prueba #1: Funcionamiento normal básico");
    #20 sensor_entrance = 1; // Llegada de vehículo 
    #20 input_password = 8'b01001001; // Ingresa contraseña correcta
    $display("Esperando que la compuerta se abra...");
    #20 sensor_entrance = 0; // Sensor en bajo ya que está terminando de ingresar un vehículo
    #20 sensor_exit = 1; // Sensor de que ya el vehículo ingresó
    $display("Esperando que la compuerta se cierre...");
    #20 sensor_exit = 0;
   
    
    // Prueba #2: Ingreso de PIN incorrecto menos de 3 veces
    $display("Prueba #2: Ingreso de PIN incorrecto menos de 3 veces");
    #40 sensor_entrance = 1; // Llegada de vehículo
    $display("Esperando contraseña...");
    #20 input_password = 8'b10101010; // Ingreso de primer pin incorrecto
    $display("Esperando contraseña...");
    #20 input_password = 8'b11101100; // Ingreso de segundo pin incorrecto
    $display("Esperando contraseña...");
    #20 input_password = 8'b01001001; // Ingreso de pin correcto
    // Esperar a que la compuerta se abra 01001001
    $display("Esperando que la compuerta se abra...");
    #20 sensor_entrance = 0; // Sensor en bajo
    #20 sensor_exit =1;
    // Esperar a que la compuerta se cierre
    $display("Esperando que la compuerta se cierre...");
    #20 sensor_exit = 0;
   
    // Prueba #3: Ingreso de pin incorrecto 3 veces
    $display("Prueba #3: Ingreso de pin incorrecto 3 veces");
    #20 sensor_entrance = 1; // Llegada de vehículo
    #20 input_password = 8'b10101010; // Ingreso de primer pin incorrecto
    #20 input_password = 8'b11001100; // Ingreso de segundo pin incorrecto
    #20 input_password = 8'b11110000; // Ingreso de tercer pin incorrecto
    #30 input_password = 8'b01001001; // Ingresa contraseña correcta
    $display("Esperando que la compuerta se abra...");
    #20 sensor_entrance = 0; // Sensor en bajo ya que está terminando de ingresar un vehículo
    #20 sensor_exit = 1; // Sensor de que ya el vehículo ingresó
    $display("Esperando que la compuerta se cierre...");
    #20 sensor_exit = 0;
  
    //Prueba #4  
    $display("Prueba #4: alarma de bloqueo"); 
    #20 sensor_exit = 1;
    #20 sensor_entrance = 1; // Llegada de vehículo
    #20 input_password = 8'b10101010; // Ingreso de pin incorrecto PRUEBA PUEDE CAMBIARSE
    #20 input_password = 8'b11001100; // Ingreso de pin incorrecto
    #20 input_password = 8'b01001001; // Ingresa contraseña correcta
    $display("Esperando que la compuerta se abra...");
    #20 sensor_entrance = 0; // Sensor en bajo
    #20 sensor_exit = 1; // Sensor de que ya el vehículo ingresó
    $display("Esperando que la compuerta se cierre...");
    #20 sensor_exit = 0;
    #400 $finish; // Termina la simulación
end

always #10 clk = ~clk; // clk cada 5 unidades de tiempo
endmodule

TAREA2/retardos/cmos_cells.v
module BUF(A, Y);
  input A;
  output Y;
  assign  #1 Y = A;
endmodule

module NOT(A, Y);
  input A;
  output Y;
  assign #2 Y = ~A;
endmodule

module NAND(A, B, Y);
  input A, B;
  output Y;
  assign #2 Y = ~(A & B);
endmodule

module NOR(A, B, Y);
  input A, B;
  output Y;
  assign  #2 Y = ~(A | B);
endmodule

module DFF(C, D, Q);
  input C, D; 
  output reg Q;
  always @(posedge C) #5 Q <= D;
endmodule

TAREA2/retardos/controller_synth_cmos.v
/* Generated by Yosys 0.40+45 (git sha1 dd2195543, g++ 11.4.0-1ubuntu1~22.04 -fPIC -Os) */

(* top =  1  *)
(* src = "controller.v:1.1-112.10" *)
module controller(clk, reset, sensor_entrance, sensor_exit, input_password, gate_open, gate_close, alarm_wrong_pin, alarm_block);
  wire _000_;
  wire _001_;
  wire _002_;
  wire _003_;
  wire _004_;
  wire _005_;
  wire _006_;
  wire _007_;
  wire _008_;
  wire _009_;
  wire _010_;
  wire _011_;
  wire _012_;
  wire _013_;
  wire _014_;
  wire _015_;
  wire _016_;
  wire _017_;
  wire _018_;
  wire _019_;
  wire _020_;
  wire _021_;
  wire _022_;
  wire _023_;
  wire _024_;
  wire _025_;
  wire _026_;
  wire _027_;
  wire _028_;
  wire _029_;
  wire _030_;
  wire _031_;
  wire _032_;
  wire _033_;
  wire _034_;
  wire _035_;
  wire _036_;
  wire _037_;
  wire _038_;
  wire _039_;
  wire _040_;
  wire _041_;
  wire _042_;
  wire _043_;
  wire _044_;
  wire _045_;
  wire _046_;
  wire _047_;
  wire _048_;
  wire _049_;
  wire _050_;
  wire _051_;
  wire _052_;
  wire _053_;
  wire _054_;
  wire _055_;
  wire _056_;
  wire _057_;
  wire _058_;
  wire _059_;
  wire _060_;
  wire _061_;
  wire _062_;
  wire _063_;
  wire _064_;
  wire _065_;
  (* src = "controller.v:16.52-16.63" *)
  output alarm_block;
  wire alarm_block;
  (* src = "controller.v:16.23-16.38" *)
  output alarm_wrong_pin;
  wire alarm_wrong_pin;
  (* src = "controller.v:14.7-14.10" *)
  input clk;
  wire clk;
  (* src = "controller.v:19.11-19.17" *)
  wire [2:0] count0;
  (* src = "controller.v:18.11-18.24" *)
  wire [2:0] current_state;
  (* src = "controller.v:16.40-16.50" *)
  output gate_close;
  wire gate_close;
  (* src = "controller.v:16.12-16.21" *)
  output gate_open;
  wire gate_open;
  (* src = "controller.v:15.13-15.27" *)
  input [7:0] input_password;
  wire [7:0] input_password;
  (* src = "controller.v:14.12-14.17" *)
  input reset;
  wire reset;
  (* src = "controller.v:14.19-14.34" *)
  input sensor_entrance;
  wire sensor_entrance;
  (* src = "controller.v:14.36-14.47" *)
  input sensor_exit;
  wire sensor_exit;
  NOT _066_ (
    .A(count0[2]),
    .Y(_005_)
  );
  NOT _067_ (
    .A(count0[1]),
    .Y(_006_)
  );
  NOT _068_ (
    .A(count0[0]),
    .Y(_007_)
  );
  NOT _069_ (
    .A(current_state[2]),
    .Y(_008_)
  );
  NOT _070_ (
    .A(current_state[1]),
    .Y(_009_)
  );
  NOT _071_ (
    .A(current_state[0]),
    .Y(_010_)
  );
  NOT _072_ (
    .A(reset),
    .Y(_011_)
  );
  NOT _073_ (
    .A(input_password[6]),
    .Y(_012_)
  );
  NOT _074_ (
    .A(input_password[1]),
    .Y(_013_)
  );
  NOT _075_ (
    .A(sensor_entrance),
    .Y(_014_)
  );
  NOR _076_ (
    .A(current_state[2]),
    .B(current_state[1]),
    .Y(_015_)
  );
  NAND _077_ (
    .A(_010_),
    .B(_015_),
    .Y(_016_)
  );
  NOR _078_ (
    .A(_014_),
    .B(_016_),
    .Y(_017_)
  );
  NAND _079_ (
    .A(current_state[0]),
    .B(_015_),
    .Y(_018_)
  );
  NOT _080_ (
    .A(_018_),
    .Y(_019_)
  );
  NAND _081_ (
    .A(current_state[1]),
    .B(current_state[0]),
    .Y(_020_)
  );
  NOR _082_ (
    .A(current_state[2]),
    .B(_009_),
    .Y(_021_)
  );
  NOR _083_ (
    .A(current_state[2]),
    .B(_020_),
    .Y(alarm_block)
  );
  NOT _084_ (
    .A(alarm_block),
    .Y(_022_)
  );
  NAND _085_ (
    .A(_008_),
    .B(current_state[0]),
    .Y(_023_)
  );
  NOR _086_ (
    .A(input_password[2]),
    .B(input_password[4]),
    .Y(_024_)
  );
  NOR _087_ (
    .A(input_password[5]),
    .B(input_password[7]),
    .Y(_025_)
  );
  NAND _088_ (
    .A(_024_),
    .B(_025_),
    .Y(_026_)
  );
  NOT _089_ (
    .A(_026_),
    .Y(_027_)
  );
  NAND _090_ (
    .A(input_password[0]),
    .B(input_password[3]),
    .Y(_028_)
  );
  NOT _091_ (
    .A(_028_),
    .Y(_029_)
  );
  NOR _092_ (
    .A(_012_),
    .B(input_password[1]),
    .Y(_030_)
  );
  NAND _093_ (
    .A(input_password[6]),
    .B(_013_),
    .Y(_031_)
  );
  NOR _094_ (
    .A(_028_),
    .B(_031_),
    .Y(_032_)
  );
  NAND _095_ (
    .A(_029_),
    .B(_030_),
    .Y(_033_)
  );
  NOR _096_ (
    .A(_026_),
    .B(_033_),
    .Y(_034_)
  );
  NAND _097_ (
    .A(_027_),
    .B(_032_),
    .Y(_035_)
  );
  NOR _098_ (
    .A(_023_),
    .B(_034_),
    .Y(_036_)
  );
  NOR _099_ (
    .A(_017_),
    .B(_036_),
    .Y(_037_)
  );
  NOR _100_ (
    .A(reset),
    .B(_037_),
    .Y(_000_)
  );
  NOR _101_ (
    .A(_009_),
    .B(current_state[0]),
    .Y(_038_)
  );
  NAND _102_ (
    .A(_008_),
    .B(_038_),
    .Y(_039_)
  );
  NOT _103_ (
    .A(_039_),
    .Y(gate_open)
  );
  NOR _104_ (
    .A(sensor_exit),
    .B(_039_),
    .Y(_040_)
  );
  NAND _105_ (
    .A(sensor_exit),
    .B(_017_),
    .Y(_041_)
  );
  NOR _106_ (
    .A(_018_),
    .B(_035_),
    .Y(_042_)
  );
  NOR _107_ (
    .A(alarm_block),
    .B(_042_),
    .Y(_043_)
  );
  NAND _108_ (
    .A(_041_),
    .B(_043_),
    .Y(_044_)
  );
  NOR _109_ (
    .A(_040_),
    .B(_044_),
    .Y(_045_)
  );
  NOR _110_ (
    .A(reset),
    .B(_045_),
    .Y(_001_)
  );
  NAND _111_ (
    .A(count0[1]),
    .B(count0[0]),
    .Y(_046_)
  );
  NOT _112_ (
    .A(_046_),
    .Y(_047_)
  );
  NAND _113_ (
    .A(_005_),
    .B(_046_),
    .Y(_048_)
  );
  NOR _114_ (
    .A(_034_),
    .B(_048_),
    .Y(_049_)
  );
  NOR _115_ (
    .A(_022_),
    .B(_049_),
    .Y(_050_)
  );
  NOR _116_ (
    .A(_021_),
    .B(_036_),
    .Y(_051_)
  );
  NOR _117_ (
    .A(_050_),
    .B(_051_),
    .Y(_052_)
  );
  NOT _118_ (
    .A(_052_),
    .Y(_053_)
  );
  NOR _119_ (
    .A(_007_),
    .B(_053_),
    .Y(_054_)
  );
  NAND _120_ (
    .A(_005_),
    .B(_036_),
    .Y(_055_)
  );
  NAND _121_ (
    .A(_007_),
    .B(_055_),
    .Y(_056_)
  );
  NAND _122_ (
    .A(_011_),
    .B(_056_),
    .Y(_057_)
  );
  NOR _123_ (
    .A(_054_),
    .B(_057_),
    .Y(_002_)
  );
  NOR _124_ (
    .A(_006_),
    .B(_052_),
    .Y(_058_)
  );
  NOR _125_ (
    .A(_047_),
    .B(_055_),
    .Y(_059_)
  );
  NOR _126_ (
    .A(_058_),
    .B(_059_),
    .Y(_060_)
  );
  NOR _127_ (
    .A(count0[1]),
    .B(count0[0]),
    .Y(_061_)
  );
  NOR _128_ (
    .A(reset),
    .B(_061_),
    .Y(_062_)
  );
  NOT _129_ (
    .A(_062_),
    .Y(_063_)
  );
  NOR _130_ (
    .A(_060_),
    .B(_063_),
    .Y(_003_)
  );
  NAND _131_ (
    .A(count0[2]),
    .B(_011_),
    .Y(_064_)
  );
  NOR _132_ (
    .A(_052_),
    .B(_064_),
    .Y(_004_)
  );
  NOR _133_ (
    .A(current_state[2]),
    .B(_038_),
    .Y(gate_close)
  );
  NAND _134_ (
    .A(_019_),
    .B(_048_),
    .Y(_065_)
  );
  NOR _135_ (
    .A(_034_),
    .B(_065_),
    .Y(alarm_wrong_pin)
  );
  (* src = "controller.v:29.1-37.4" *)
  DFF _136_ (
    .C(clk),
    .D(_000_),
    .Q(current_state[0])
  );
  (* src = "controller.v:29.1-37.4" *)
  DFF _137_ (
    .C(clk),
    .D(_001_),
    .Q(current_state[1])
  );
  (* src = "controller.v:29.1-37.4" *)
  DFF _138_ (
    .C(clk),
    .D(1'h0),
    .Q(current_state[2])
  );
  (* src = "controller.v:29.1-37.4" *)
  DFF _139_ (
    .C(clk),
    .D(_002_),
    .Q(count0[0])
  );
  (* src = "controller.v:29.1-37.4" *)
  DFF _140_ (
    .C(clk),
    .D(_003_),
    .Q(count0[1])
  );
  (* src = "controller.v:29.1-37.4" *)
  DFF _141_ (
    .C(clk),
    .D(_004_),
    .Q(count0[2])
  );
endmodule

TAREA2/retardos/testbench.v
`include "tester.v"
`include "controller_synth_cmos.v"
`include "cmos_cells.v"

module controller_tb;
wire clk;                  //Aquí se establecen los cables de las entradas y las salidas del sistema
wire reset;
wire sensor_entrance;
wire sensor_exit;
wire [7:0] input_password;
wire gate_open;
wire alarm_wrong_pin;
wire gate_close;
wire alarm_block;

initial begin
	$dumpfile("resultados.vcd"); // Se generan los resultados para poder verlos con gtkwave
	$dumpvars(-1, U0);
	$monitor ("sensor_entrance=%b,sensor_exit=%b,gate_open=%b,gate_close=%b,alarm_pin=%b, alarm_block=%b", sensor_entrance, sensor_exit, gate_open, gate_close, alarm_wrong_pin, alarm_block); // Se despliega en consola el funcionamiento del sistema
  end
// Instanciar el controlador
controller U0 (
    .clk(clk),
    .reset(reset),
    .sensor_entrance(sensor_entrance),
    .sensor_exit(sensor_exit),
    .input_password(input_password),
    .gate_open(gate_open),
    .alarm_wrong_pin(alarm_wrong_pin),
    .gate_close(gate_close),
    .alarm_block(alarm_block)
);

// Instanciar el probador
tester P0 (
    .clk(clk),
    .reset(reset),
    .sensor_entrance(sensor_entrance),
    .sensor_exit(sensor_exit),
    .input_password(input_password),
    .gate_open(gate_open),
    .alarm_wrong_pin(alarm_wrong_pin),
    .gate_close(gate_close),
    .alarm_block(alarm_block)
);

endmodule

TAREA2/retardos/resultados.vcd
$date
	Sat May  4 19:52:02 2024
$end
$version
	Icarus Verilog
$end
$timescale
	1s
$end
$scope module controller_tb $end
$scope module U0 $end
$var wire 1 ! clk $end
$var wire 8 " input_password [7:0] $end
$var wire 1 # reset $end
$var wire 1 $ sensor_entrance $end
$var wire 1 % sensor_exit $end
$var wire 1 & gate_open $end
$var wire 1 ' gate_close $end
$var wire 3 ( current_state [2:0] $end
$var wire 3 ) count0 [2:0] $end
$var wire 1 * alarm_wrong_pin $end
$var wire 1 + alarm_block $end
$var wire 1 , _065_ $end
$var wire 1 - _064_ $end
$var wire 1 . _063_ $end
$var wire 1 / _062_ $end
$var wire 1 0 _061_ $end
$var wire 1 1 _060_ $end
$var wire 1 2 _059_ $end
$var wire 1 3 _058_ $end
$var wire 1 4 _057_ $end
$var wire 1 5 _056_ $end
$var wire 1 6 _055_ $end
$var wire 1 7 _054_ $end
$var wire 1 8 _053_ $end
$var wire 1 9 _052_ $end
$var wire 1 : _051_ $end
$var wire 1 ; _050_ $end
$var wire 1 < _049_ $end
$var wire 1 = _048_ $end
$var wire 1 > _047_ $end
$var wire 1 ? _046_ $end
$var wire 1 @ _045_ $end
$var wire 1 A _044_ $end
$var wire 1 B _043_ $end
$var wire 1 C _042_ $end
$var wire 1 D _041_ $end
$var wire 1 E _040_ $end
$var wire 1 F _039_ $end
$var wire 1 G _038_ $end
$var wire 1 H _037_ $end
$var wire 1 I _036_ $end
$var wire 1 J _035_ $end
$var wire 1 K _034_ $end
$var wire 1 L _033_ $end
$var wire 1 M _032_ $end
$var wire 1 N _031_ $end
$var wire 1 O _030_ $end
$var wire 1 P _029_ $end
$var wire 1 Q _028_ $end
$var wire 1 R _027_ $end
$var wire 1 S _026_ $end
$var wire 1 T _025_ $end
$var wire 1 U _024_ $end
$var wire 1 V _023_ $end
$var wire 1 W _022_ $end
$var wire 1 X _021_ $end
$var wire 1 Y _020_ $end
$var wire 1 Z _019_ $end
$var wire 1 [ _018_ $end
$var wire 1 \ _017_ $end
$var wire 1 ] _016_ $end
$var wire 1 ^ _015_ $end
$var wire 1 _ _014_ $end
$var wire 1 ` _013_ $end
$var wire 1 a _012_ $end
$var wire 1 b _011_ $end
$var wire 1 c _010_ $end
$var wire 1 d _009_ $end
$var wire 1 e _008_ $end
$var wire 1 f _007_ $end
$var wire 1 g _006_ $end
$var wire 1 h _005_ $end
$var wire 1 i _004_ $end
$var wire 1 j _003_ $end
$var wire 1 k _002_ $end
$var wire 1 l _001_ $end
$var wire 1 m _000_ $end
$scope module _066_ $end
$var wire 1 n A $end
$var wire 1 h Y $end
$upscope $end
$scope module _067_ $end
$var wire 1 o A $end
$var wire 1 g Y $end
$upscope $end
$scope module _068_ $end
$var wire 1 p A $end
$var wire 1 f Y $end
$upscope $end
$scope module _069_ $end
$var wire 1 q A $end
$var wire 1 e Y $end
$upscope $end
$scope module _070_ $end
$var wire 1 r A $end
$var wire 1 d Y $end
$upscope $end
$scope module _071_ $end
$var wire 1 s A $end
$var wire 1 c Y $end
$upscope $end
$scope module _072_ $end
$var wire 1 # A $end
$var wire 1 b Y $end
$upscope $end
$scope module _073_ $end
$var wire 1 t A $end
$var wire 1 a Y $end
$upscope $end
$scope module _074_ $end
$var wire 1 u A $end
$var wire 1 ` Y $end
$upscope $end
$scope module _075_ $end
$var wire 1 $ A $end
$var wire 1 _ Y $end
$upscope $end
$scope module _076_ $end
$var wire 1 v A $end
$var wire 1 w B $end
$var wire 1 ^ Y $end
$upscope $end
$scope module _077_ $end
$var wire 1 c A $end
$var wire 1 ^ B $end
$var wire 1 ] Y $end
$upscope $end
$scope module _078_ $end
$var wire 1 _ A $end
$var wire 1 ] B $end
$var wire 1 \ Y $end
$upscope $end
$scope module _079_ $end
$var wire 1 x A $end
$var wire 1 ^ B $end
$var wire 1 [ Y $end
$upscope $end
$scope module _080_ $end
$var wire 1 [ A $end
$var wire 1 Z Y $end
$upscope $end
$scope module _081_ $end
$var wire 1 y A $end
$var wire 1 z B $end
$var wire 1 Y Y $end
$upscope $end
$scope module _082_ $end
$var wire 1 { A $end
$var wire 1 d B $end
$var wire 1 X Y $end
$upscope $end
$scope module _083_ $end
$var wire 1 | A $end
$var wire 1 Y B $end
$var wire 1 + Y $end
$upscope $end
$scope module _084_ $end
$var wire 1 + A $end
$var wire 1 W Y $end
$upscope $end
$scope module _085_ $end
$var wire 1 e A $end
$var wire 1 } B $end
$var wire 1 V Y $end
$upscope $end
$scope module _086_ $end
$var wire 1 ~ A $end
$var wire 1 !" B $end
$var wire 1 U Y $end
$upscope $end
$scope module _087_ $end
$var wire 1 "" A $end
$var wire 1 #" B $end
$var wire 1 T Y $end
$upscope $end
$scope module _088_ $end
$var wire 1 U A $end
$var wire 1 T B $end
$var wire 1 S Y $end
$upscope $end
$scope module _089_ $end
$var wire 1 S A $end
$var wire 1 R Y $end
$upscope $end
$scope module _090_ $end
$var wire 1 $" A $end
$var wire 1 %" B $end
$var wire 1 Q Y $end
$upscope $end
$scope module _091_ $end
$var wire 1 Q A $end
$var wire 1 P Y $end
$upscope $end
$scope module _092_ $end
$var wire 1 a A $end
$var wire 1 &" B $end
$var wire 1 O Y $end
$upscope $end
$scope module _093_ $end
$var wire 1 '" A $end
$var wire 1 ` B $end
$var wire 1 N Y $end
$upscope $end
$scope module _094_ $end
$var wire 1 Q A $end
$var wire 1 N B $end
$var wire 1 M Y $end
$upscope $end
$scope module _095_ $end
$var wire 1 P A $end
$var wire 1 O B $end
$var wire 1 L Y $end
$upscope $end
$scope module _096_ $end
$var wire 1 S A $end
$var wire 1 L B $end
$var wire 1 K Y $end
$upscope $end
$scope module _097_ $end
$var wire 1 R A $end
$var wire 1 M B $end
$var wire 1 J Y $end
$upscope $end
$scope module _098_ $end
$var wire 1 V A $end
$var wire 1 K B $end
$var wire 1 I Y $end
$upscope $end
$scope module _099_ $end
$var wire 1 \ A $end
$var wire 1 I B $end
$var wire 1 H Y $end
$upscope $end
$scope module _100_ $end
$var wire 1 # A $end
$var wire 1 H B $end
$var wire 1 m Y $end
$upscope $end
$scope module _101_ $end
$var wire 1 d A $end
$var wire 1 (" B $end
$var wire 1 G Y $end
$upscope $end
$scope module _102_ $end
$var wire 1 e A $end
$var wire 1 G B $end
$var wire 1 F Y $end
$upscope $end
$scope module _103_ $end
$var wire 1 F A $end
$var wire 1 & Y $end
$upscope $end
$scope module _104_ $end
$var wire 1 % A $end
$var wire 1 F B $end
$var wire 1 E Y $end
$upscope $end
$scope module _105_ $end
$var wire 1 % A $end
$var wire 1 \ B $end
$var wire 1 D Y $end
$upscope $end
$scope module _106_ $end
$var wire 1 [ A $end
$var wire 1 J B $end
$var wire 1 C Y $end
$upscope $end
$scope module _107_ $end
$var wire 1 + A $end
$var wire 1 C B $end
$var wire 1 B Y $end
$upscope $end
$scope module _108_ $end
$var wire 1 D A $end
$var wire 1 B B $end
$var wire 1 A Y $end
$upscope $end
$scope module _109_ $end
$var wire 1 E A $end
$var wire 1 A B $end
$var wire 1 @ Y $end
$upscope $end
$scope module _110_ $end
$var wire 1 # A $end
$var wire 1 @ B $end
$var wire 1 l Y $end
$upscope $end
$scope module _111_ $end
$var wire 1 )" A $end
$var wire 1 *" B $end
$var wire 1 ? Y $end
$upscope $end
$scope module _112_ $end
$var wire 1 ? A $end
$var wire 1 > Y $end
$upscope $end
$scope module _113_ $end
$var wire 1 h A $end
$var wire 1 ? B $end
$var wire 1 = Y $end
$upscope $end
$scope module _114_ $end
$var wire 1 K A $end
$var wire 1 = B $end
$var wire 1 < Y $end
$upscope $end
$scope module _115_ $end
$var wire 1 W A $end
$var wire 1 < B $end
$var wire 1 ; Y $end
$upscope $end
$scope module _116_ $end
$var wire 1 X A $end
$var wire 1 I B $end
$var wire 1 : Y $end
$upscope $end
$scope module _117_ $end
$var wire 1 ; A $end
$var wire 1 : B $end
$var wire 1 9 Y $end
$upscope $end
$scope module _118_ $end
$var wire 1 9 A $end
$var wire 1 8 Y $end
$upscope $end
$scope module _119_ $end
$var wire 1 f A $end
$var wire 1 8 B $end
$var wire 1 7 Y $end
$upscope $end
$scope module _120_ $end
$var wire 1 h A $end
$var wire 1 I B $end
$var wire 1 6 Y $end
$upscope $end
$scope module _121_ $end
$var wire 1 f A $end
$var wire 1 6 B $end
$var wire 1 5 Y $end
$upscope $end
$scope module _122_ $end
$var wire 1 b A $end
$var wire 1 5 B $end
$var wire 1 4 Y $end
$upscope $end
$scope module _123_ $end
$var wire 1 7 A $end
$var wire 1 4 B $end
$var wire 1 k Y $end
$upscope $end
$scope module _124_ $end
$var wire 1 g A $end
$var wire 1 9 B $end
$var wire 1 3 Y $end
$upscope $end
$scope module _125_ $end
$var wire 1 > A $end
$var wire 1 6 B $end
$var wire 1 2 Y $end
$upscope $end
$scope module _126_ $end
$var wire 1 3 A $end
$var wire 1 2 B $end
$var wire 1 1 Y $end
$upscope $end
$scope module _127_ $end
$var wire 1 +" A $end
$var wire 1 ," B $end
$var wire 1 0 Y $end
$upscope $end
$scope module _128_ $end
$var wire 1 # A $end
$var wire 1 0 B $end
$var wire 1 / Y $end
$upscope $end
$scope module _129_ $end
$var wire 1 / A $end
$var wire 1 . Y $end
$upscope $end
$scope module _130_ $end
$var wire 1 1 A $end
$var wire 1 . B $end
$var wire 1 j Y $end
$upscope $end
$scope module _131_ $end
$var wire 1 -" A $end
$var wire 1 b B $end
$var wire 1 - Y $end
$upscope $end
$scope module _132_ $end
$var wire 1 9 A $end
$var wire 1 - B $end
$var wire 1 i Y $end
$upscope $end
$scope module _133_ $end
$var wire 1 ." A $end
$var wire 1 G B $end
$var wire 1 ' Y $end
$upscope $end
$scope module _134_ $end
$var wire 1 Z A $end
$var wire 1 = B $end
$var wire 1 , Y $end
$upscope $end
$scope module _135_ $end
$var wire 1 K A $end
$var wire 1 , B $end
$var wire 1 * Y $end
$upscope $end
$scope module _136_ $end
$var wire 1 ! C $end
$var wire 1 m D $end
$var reg 1 /" Q $end
$upscope $end
$scope module _137_ $end
$var wire 1 ! C $end
$var wire 1 l D $end
$var reg 1 0" Q $end
$upscope $end
$scope module _138_ $end
$var wire 1 ! C $end
$var wire 1 1" D $end
$var reg 1 2" Q $end
$upscope $end
$scope module _139_ $end
$var wire 1 ! C $end
$var wire 1 k D $end
$var reg 1 3" Q $end
$upscope $end
$scope module _140_ $end
$var wire 1 ! C $end
$var wire 1 j D $end
$var reg 1 4" Q $end
$upscope $end
$scope module _141_ $end
$var wire 1 ! C $end
$var wire 1 i D $end
$var reg 1 5" Q $end
$upscope $end
$upscope $end
$upscope $end
$enddefinitions $end
#0
$dumpvars
x5"
x4"
x3"
x2"
01"
x0"
x/"
x."
x-"
x,"
x+"
x*"
x)"
x("
x'"
x&"
x%"
x$"
x#"
x""
x!"
x~
x}
x|
x{
xz
xy
xx
xw
xv
xu
xt
xs
xr
xq
xp
xo
xn
xm
xl
xk
xj
xi
xh
xg
xf
xe
xd
xc
xb
xa
x`
x_
x^
x]
x\
x[
xZ
xY
xX
xW
xV
xU
xT
xS
xR
xQ
xP
xO
xN
xM
xL
xK
xJ
xI
xH
xG
xF
xE
xD
xC
xB
xA
x@
x?
x>
x=
x<
x;
x:
x9
x8
x7
x6
x5
x4
x3
x2
x1
x0
x/
x.
x-
x,
x+
x*
bx )
bx (
x'
x&
0%
0$
0#
bx "
0!
$end
#2
1D
1_
1b
#4
0\
#10
1!
1#
#12
0m
0l
0/
0b
#14
14
1-
1.
#15
0("
0}
0z
0x
0s
0y
0w
0r
0."
0|
0{
0v
0q
0/"
00"
b0 (
02"
#16
0k
0i
0j
#17
1V
1[
1Y
1^
1c
1d
1e
#19
0I
0C
0+
0]
0X
0G
0Z
#20
0!
#21
1H
16
1B
1:
1F
1'
1,
1W
#23
02
0A
09
0E
0*
0;
0&
#25
1@
18
#27
07
#30
1!
0#
#32
x/
1b
#34
x4
x-
x.
#35
0-"
0n
0+"
0)"
0o
0,"
0*"
0p
05"
04"
b0 )
03"
#36
xk
xi
xj
#37
1-
10
1?
1h
1g
1f
#39
0i
0/
0=
03
05
0>
#40
0!
#41
11
14
1.
#43
0k
0j
#50
1!
1$
#52
0_
#54
1\
#56
0H
#58
1m
#60
0!
#70
1t
0u
0~
0!"
0""
0#"
1$"
1%"
0&"
1'"
1!
b1001001 "
#72
1U
1T
0Q
0a
1`
#74
0S
1O
0N
1P
#75
1("
1}
1z
1x
1s
b1 (
1/"
#76
1M
0L
1R
#77
0V
0[
0c
#78
1K
0J
#79
1]
1Z
#80
0<
1C
0!
#81
0\
#82
0B
#83
1H
#84
1A
#85
0m
#86
0@
#88
1l
#90
1!
0$
#92
1_
#95
0("
0}
0z
0x
0s
1y
1w
1r
0/"
b10 (
10"
#97
1V
1[
0^
1c
0d
#99
0C
1X
1G
0Z
#100
0!
#101
1B
0:
0F
0'
#103
0A
19
1E
1&
#105
08
#110
1!
1%
#112
0E
#114
1@
#116
0l
#120
0!
#130
1!
0%
#132
1E
#134
0@
#135
0y
0w
0r
b0 (
00"
#136
1l
#137
1^
1d
#139
0]
0X
0G
#140
0!
#141
1:
1F
1'
#143
09
0E
0&
#145
1@
18
#147
0l
#150
1!
#160
0!
#170
1!
1$
#172
0_
#174
1\
#176
0H
#178
1m
#180
0!
#190
0t
1u
1""
1#"
0$"
1&"
0'"
1!
b10101010 "
#192
0T
1Q
0O
1N
1a
0`
#194
1S
1L
0M
0P
#195
1("
1}
1z
1x
1s
b1 (
1/"
#196
0K
1J
0R
#197
0V
0[
0c
#198
1<
#199
1I
1]
1Z
#200
0!
#201
0:
06
0\
#203
19
15
12
#205
04
01
08
#207
1k
#210
1t
0u
1~
0&"
1'"
1!
b11101100 "
#212
0U
0a
1`
#214
1O
0N
#215
1,"
1*"
1p
b1 )
13"
#217
00
0f
#219
1/
17
#220
0!
#221
0k
0.
#223
1j
#230
0~
0""
0#"
1$"
1!
b1001001 "
#232
1U
1T
0Q
#234
0S
1M
1P
#235
1+"
1)"
1o
0,"
0*"
0p
14"
b10 )
03"
#236
0L
1R
#237
0g
1f
#238
1K
0J
#239
07
#240
0I
0<
1C
0!
#241
1k
#242
1H
1:
16
0B
#244
0m
09
05
02
1A
#246
13
14
11
0@
18
#248
01
0k
0j
1l
#250
1j
1!
0$
#252
1_
#255
0("
0}
0z
0x
0s
1y
1w
1r
0/"
b10 (
10"
#257
1V
1[
0^
1c
0d
#259
0C
1X
1G
0Z
#260
0!
#261
1B
0:
0F
0'
#263
0A
19
1E
1&
#265
03
08
#267
11
#269
0j
#270
1!
1%
#272
0E
#274
1@
#275
0+"
0)"
0o
b0 )
04"
#276
0l
#277
10
1g
#279
0/
#280
0!
#281
1.
#290
1!
0%
#292
1E
#294
0@
#295
0y
0w
0r
b0 (
00"
#296
1l
#297
1^
1d
#299
0]
0X
0G
#300
0!
#301
1:
1F
1'
#303
09
0E
0&
#305
1@
18
#307
0l
#310
1!
1$
#312
0_
#314
1\
#316
0H
#318
1m
#320
0!
#330
0t
1u
1""
1#"
0$"
1&"
0'"
1!
b10101010 "
#332
0T
1Q
0O
1N
1a
0`
#334
1S
1L
0M
0P
#335
1("
1}
1z
1x
1s
b1 (
1/"
#336
0K
1J
0R
#337
0V
0[
0c
#338
1<
#339
1I
1]
1Z
#340
0!
#341
0:
06
0\
#343
19
15
12
#345
04
01
08
#347
1k
#350
1t
0u
1~
0""
0&"
1'"
1!
b11001100 "
#352
0U
0a
1`
#354
1O
0N
#355
1,"
1*"
1p
b1 )
13"
#357
00
0f
#359
1/
17
#360
0!
#361
0k
0.
#363
1j
#370
0~
1!"
1""
0%"
1!
b11110000 "
#375
0,"
0*"
0p
1+"
1)"
1o
03"
b10 )
14"
#377
1f
0g
#379
07
#380
0!
