TAREA3/cmos_version/tester.v
module tester ( 
	    CLK,
    	RESET,
    	TARJETA_RECIBIDA,
    	PIN,
    	DIGITO,
    	DIGITO_STB,
    	PIN_INCORRECTO,
        ADVERTENCIA,
        BLOQUEO, 
        TIPO_TRANS,
        MONTO,
        BALANCE_ACTUALIZADO,
        MONTO_STB,
        ENTREGAR_DINERO,
        FONDOS_INSUFICIENTES
);


output CLK, RESET, TARJETA_RECIBIDA, DIGITO_STB, TIPO_TRANS, MONTO_STB;
output [31:0] MONTO; // Las salidas de este módulo son las entradas que le llegarán al controlador
output [3:0] DIGITO;
output [15:0] PIN;

input PIN_INCORRECTO;
input ADVERTENCIA;
input BLOQUEO;
input BALANCE_ACTUALIZADO;
input ENTREGAR_DINERO;
input FONDOS_INSUFICIENTES;


reg CLK, RESET, TARJETA_RECIBIDA, DIGITO_STB, TIPO_TRANS, MONTO_STB; // Las salidas de este módulo son las entradas que le llegarán al controlador
reg [3:0] DIGITO;
reg [15:0] PIN;
reg [31:0] MONTO;
 
wire PIN_INCORRECTO;
wire ADVERTENCIA;
wire BLOQUEO;
wire BALANCE_ACTUALIZADO;
wire FONDOS_INSUFICIENTES;
wire ENTREGAR_DINERO;


// Secuencia de pruebas 
initial begin
    // Inicialización
   	CLK = 0;
        RESET = 0;
        TARJETA_RECIBIDA = 0;
        TIPO_TRANS = 0;
        DIGITO_STB = 0;
        MONTO_STB = 0;
	
	#20 RESET = 1;
        
        // Prueba 1: Introducir 3 pines incorrectos y bloqueo
        #5 TARJETA_RECIBIDA = 1;
        #10 PIN = 16'b0011010001110011; // Del carné B53473 PRUEBA
        #20 DIGITO_STB = 1; DIGITO = 4'b0001;  #10 DIGITO_STB = 0; //Ingreso de un DIGITO cada ciclo de reloj
        #10 DIGITO_STB = 1; DIGITO = 4'b0011;  #10 DIGITO_STB = 0;
        #10 DIGITO_STB = 1; DIGITO = 4'b0111;  #10 DIGITO_STB = 0;
        #10 DIGITO_STB = 1; DIGITO = 4'b1000;  #10 DIGITO_STB = 0;
     
        //#10 TARJETA_RECIBIDA = 0;
        //#10 TARJETA_RECIBIDA = 1;
        #20 DIGITO_STB = 1; DIGITO = 4'b0001;  #10 DIGITO_STB = 0; //Ingreso de un DIGITO cada ciclo de reloj
        #10 DIGITO_STB = 1; DIGITO = 4'b0011;  #10 DIGITO_STB = 0;
        #10 DIGITO_STB = 1; DIGITO = 4'b0111;  #10 DIGITO_STB = 0;
        #10 DIGITO_STB = 1; DIGITO = 4'b1000;  #10 DIGITO_STB = 0;

        //#10 TARJETA_RECIBIDA = 0;
        //#10 TARJETA_RECIBIDA = 1;
        #20 DIGITO_STB = 1; DIGITO = 4'b0001;  #10 DIGITO_STB = 0; //Ingreso de un DIGITO cada ciclo de reloj
        #10 DIGITO_STB = 1; DIGITO = 4'b0011;  #10 DIGITO_STB = 0;
        #10 DIGITO_STB = 1; DIGITO = 4'b0111;  #10 DIGITO_STB = 0;
        #10 DIGITO_STB = 1; DIGITO = 4'b1000;  #10 DIGITO_STB = 0;
        #10 TARJETA_RECIBIDA = 0;
        #10 DIGITO = 0;
        #20 RESET = 0;
        #10 RESET = 1;
        
        // Prueba #2: Pin correcto y deposito
        #10 TARJETA_RECIBIDA = 1;
        #20 DIGITO = 4'b0011; DIGITO_STB = 1; #10 DIGITO_STB = 0; //Ingreso de un DIGITO cada ciclo de reloj
        #10 DIGITO = 4'b0100; DIGITO_STB = 1; #10 DIGITO_STB = 0;
        #10 DIGITO = 4'b0111; DIGITO_STB = 1; #10 DIGITO_STB = 0;
        #10 DIGITO = 4'b0011; DIGITO_STB = 1; #10 DIGITO_STB = 0;
        #20 TIPO_TRANS = 0; MONTO = 32'b00000000000000000000011111010000; MONTO_STB = 1; //Ingreso del tipo de trans, el Monto y la señal de Monto
        #10 MONTO_STB = 0; MONTO = 32'b0; // Señal de Monto en 1 solamente por un ciclo de reloj
        #10 TARJETA_RECIBIDA = 0;
        #10 DIGITO = 0;
        
        // Prueba #3: Dos pines incorrectos, pin correcto y retiro exitoso
        #10 TARJETA_RECIBIDA = 1;
        #20 DIGITO_STB = 1; DIGITO = 4'b0001;  #10 DIGITO_STB = 0; //Ingreso de un DIGITO cada ciclo de reloj
        #10 DIGITO_STB = 1; DIGITO = 4'b0011;  #10 DIGITO_STB = 0;
        #10 DIGITO_STB = 1; DIGITO = 4'b0111;  #10 DIGITO_STB = 0;
        #10 DIGITO_STB = 1; DIGITO = 4'b1000;  #10 DIGITO_STB = 0;
        //#10 TARJETA_RECIBIDA = 0;
        //#10 TARJETA_RECIBIDA = 1;
        
        #20 DIGITO_STB = 1; DIGITO = 4'b0001;  #10 DIGITO_STB = 0; //Ingreso de un DIGITO cada ciclo de reloj
        #10 DIGITO_STB = 1; DIGITO = 4'b0011;  #10 DIGITO_STB = 0;
        #10 DIGITO_STB = 1; DIGITO = 4'b0111;  #10 DIGITO_STB = 0;
        #10 DIGITO_STB = 1; DIGITO = 4'b1000;  #10 DIGITO_STB = 0;
      
        //#10 TARJETA_RECIBIDA = 0;
        //#10 TARJETA_RECIBIDA = 1;
        #20 DIGITO = 4'b0011; DIGITO_STB = 1; #10 DIGITO_STB = 0; //Ingreso de un DIGITO cada ciclo de reloj
        #10 DIGITO = 4'b0100; DIGITO_STB = 1; #10 DIGITO_STB = 0;
        #10 DIGITO = 4'b0111; DIGITO_STB = 1; #10 DIGITO_STB = 0;
        #10 DIGITO = 4'b0011; DIGITO_STB = 1; #10 DIGITO_STB = 0;
        #10 TIPO_TRANS = 1; //Ingreso del tipo de trans, el Monto y la señal de Monto
        #10 MONTO = 32'b00000000000000000000011111010000; MONTO_STB = 1; 
        #10 MONTO_STB = 0; TARJETA_RECIBIDA = 0; // Señal de Monto en 1 solamente por un ciclo de reloj
        #10 DIGITO = 0;
      
        // Prueba #4: Pin correcto y fondos insuficientes
        #10 TARJETA_RECIBIDA = 1;
        #20 DIGITO = 4'b0011; DIGITO_STB = 1; #10 DIGITO_STB = 0; //Ingreso de un DIGITO cada ciclo de reloj
        #10 DIGITO = 4'b0100; DIGITO_STB = 1; #10 DIGITO_STB = 0;
        #10 DIGITO = 4'b0111; DIGITO_STB = 1; #10 DIGITO_STB = 0;
        #10 DIGITO = 4'b0011; DIGITO_STB = 1; #10 DIGITO_STB = 0;
        #10; //Delay de prueba
        #10 TIPO_TRANS = 1; MONTO = 32'b00000000000000000010011100010000; MONTO_STB = 1; //Ingreso del tipo de trans, el Monto y la señal de Monto
        #10 TARJETA_RECIBIDA = 0; MONTO_STB = 0; // Señal de Monto en 1 solamente por un ciclo de reloj
        #10 DIGITO = 0;
        #500 $finish;
end

always begin
 #5 CLK = !CLK;
end
endmodule

TAREA3/conductual_version/cajero.v
module controller(
    CLK,
    RESET,
    TARJETA_RECIBIDA,
    PIN,
    DIGITO,
    DIGITO_STB,
    PIN_INCORRECTO, 
    ADVERTENCIA,
    BLOQUEO,
    TIPO_TRANS,
    MONTO,
    BALANCE_ACTUALIZADO,
    MONTO_STB,
    ENTREGAR_DINERO,
    FONDOS_INSUFICIENTES
);
// Declaración de los inputs del módulo
input CLK, RESET, TARJETA_RECIBIDA, DIGITO_STB, TIPO_TRANS, MONTO_STB;
input [31:0] MONTO;
input [3:0] DIGITO;
input [15:0] PIN;

// Declaración de los outputs del módulo
output reg PIN_INCORRECTO;
output reg ADVERTENCIA;
output reg BLOQUEO;
output reg BALANCE_ACTUALIZADO;
output reg ENTREGAR_DINERO;
output reg FONDOS_INSUFICIENTES;



// Definición de estados
parameter ESTADO_INICIAL = 4'b0000;
parameter ESTADO_ESPERANDO_DIGITOS = 4'b0001;
parameter ESTADO_VERIFICACION = 4'b0010;
parameter ESTADO_AUTORIZADO = 4'b0011;
parameter ESTADO_DEPOSITO = 4'b0100;
parameter ESTADO_RETIRO = 4'b0101;
parameter ESTADO_BLOQUEO = 4'b0110;


// Declaración de registros internos
reg [63:0] BALANCE;
reg [63:0] MONTO_ext;
reg [63:0] balance_temp;
reg [3:0] estado_actual, proximo_estado;
reg [15:0] pin_interno;
reg [1:0] INTENTOS;
reg [2:0] contador_digitos;
reg [1:0] nxt_INTENTOS;
reg [2:0] nxt_contador_digitos;



// Lógica secuencial para actualizar el estado actual
always @(posedge CLK) begin
    if (!RESET) begin
        // Reiniciar valores del estado y contadores
        estado_actual <= ESTADO_INICIAL;
        pin_interno <= 16'b0000000000000000;
        INTENTOS <= 2'b00;
        contador_digitos <= 3'b000;
    end else begin
        // Actualizar estado y contadores
        estado_actual <= proximo_estado;
        contador_digitos <= nxt_contador_digitos;
        INTENTOS <= nxt_INTENTOS;
        if (DIGITO_STB) begin
            // Concatena los bits de DIGITO en pin_interno
            pin_interno <= {pin_interno[11:0], DIGITO};
            
        end
         
    end
end

// Lógica combinacional para determinar el próximo estado
always @(*) begin

    // Completando el comportamiento de cada FF para que se sostenga el estado o valor anterior
    proximo_estado = estado_actual;
    nxt_contador_digitos = contador_digitos;
    nxt_INTENTOS = INTENTOS;
    // Inicialización de las señales de interés
    PIN_INCORRECTO = 1'b0;
    ADVERTENCIA = 1'b0;
    BLOQUEO = 1'b0;
    BALANCE_ACTUALIZADO = 1'b0;
    FONDOS_INSUFICIENTES = 1'b0;
    ENTREGAR_DINERO = 1'b0;
    
    case(estado_actual)
        ESTADO_INICIAL: begin // Estado inicial que pasa al siguiente estado sólo si ha recibido una tarjeta
        nxt_INTENTOS = 0;
            MONTO_ext = 64'b0;
            if (TARJETA_RECIBIDA) begin
                proximo_estado = ESTADO_ESPERANDO_DIGITOS;
            end else begin
                proximo_estado = ESTADO_INICIAL;
            end
        end
        
        ESTADO_ESPERANDO_DIGITOS: begin
            if (DIGITO_STB) begin //Estado que espera 4 digitos ingresados con cada señal de digito
                nxt_contador_digitos = contador_digitos + 1;
            end else begin
                proximo_estado = ESTADO_ESPERANDO_DIGITOS;
            end
            if (contador_digitos == 4) begin // Se compara el pin solamente si se han ingresado 4 digitos
                nxt_INTENTOS = INTENTOS + 1; // Se incrementan los intentos cada 4 digitos ingresados
                nxt_contador_digitos = 3'b000;
                proximo_estado = ESTADO_VERIFICACION;
            end else begin
                proximo_estado = ESTADO_ESPERANDO_DIGITOS;
            end
        end

        ESTADO_VERIFICACION: begin
            if (PIN != pin_interno) begin // Si el pin no es correcto enciendo la señal de pin incorrecto
                PIN_INCORRECTO = 1'b1;
                if (INTENTOS == 2) begin //Si el pin es incorrecto y llevo dos intentos invalidos enciendo advertencia
                    ADVERTENCIA = 1;
                    proximo_estado = ESTADO_ESPERANDO_DIGITOS; // Volver al estado de espera de dígitos
                end else if (INTENTOS == 3) begin
                    proximo_estado = ESTADO_BLOQUEO; //Si el pin es incorrecto y llevo tres intentos invalidos paso a bloqueo
                end else begin
                    proximo_estado = ESTADO_ESPERANDO_DIGITOS; // Volver al estado de espera de dígitos
                end
            end else begin
                proximo_estado = ESTADO_AUTORIZADO; // Si mi pin es correcto paso a estado autorizado
            end
        end

        ESTADO_AUTORIZADO: begin // En estado autorizado obtengo un balance asociado a la tarjeta ingresada 
            BALANCE = 64'b0000000000000000000000000000000000000000000000000001001110001000;
            if (!TARJETA_RECIBIDA) begin 
            proximo_estado = ESTADO_INICIAL;
            end
            if (!TIPO_TRANS && MONTO_STB) begin // Si el tipo de transaccion está en bajo y tengo señal de Monto, paso al estado deposito
                proximo_estado = ESTADO_DEPOSITO;
            end
            if (TIPO_TRANS && MONTO_STB) begin // Si el tipo de transaccion está en alto y tengo señal de Monto, comparo MONTO con BALANCE
              MONTO_ext = {32'b0, MONTO}; // Convierto mi MONTO a 64 bits para poder comparar
              if (MONTO_ext <= BALANCE) begin // Solo retiro si mi MONTO < BALANCE
                proximo_estado = ESTADO_RETIRO;
            end
              else begin
                FONDOS_INSUFICIENTES = 1'b1; // Enciendo señal de fondos insuficientes si mi MONTO > BALANCE
                proximo_estado = ESTADO_AUTORIZADO;
            end
            end
        end
        
        
         ESTADO_DEPOSITO: begin
        // Se suma el monto al balance
        BALANCE = BALANCE + MONTO;
        // Marcar que el balance ha sido actualizado
        BALANCE_ACTUALIZADO = 1'b1;
        // Se cambia al estado inicial solo cuando MONTO_STB esté en bajo
        // Permanece en el mismo estado si tarjeta recibida está activa
        if (!TARJETA_RECIBIDA) proximo_estado = ESTADO_INICIAL;   
	end

      ESTADO_RETIRO: begin // Le resto a BALANCE el valor de MONTO y enciendo señales 
        BALANCE = BALANCE - MONTO_ext;
        ENTREGAR_DINERO = 1'b1;
        BALANCE_ACTUALIZADO = 1'b1;
        MONTO_ext = 64'b0;
        // Permanece en el mismo estado si TARJETA_RECIBIDA está activa
        if (!TARJETA_RECIBIDA) proximo_estado = ESTADO_INICIAL;
    end
    
        ESTADO_BLOQUEO: begin // Estado de bloqueo que enciende señal de bloqueo si se llega a tres intentos inválidos
            BLOQUEO = 1'b1;
            if (!RESET) begin // Sólo reseteando vuelvo al estado inicial
            proximo_estado = ESTADO_INICIAL;
            end
        end
        
        default:   proximo_estado = 4'b0000; // Si la máquina entrara en un estado inesperado, regrese al inicio.

    endcase
end

endmodule

TAREA3/conductual_version/testbench.v
`include "tester.v"
`include "cajero.v"



module controller_tb;
wire CLK;
wire RESET;
wire TARJETA_RECIBIDA;
wire [15:0] PIN;
wire [3:0] DIGITO;
wire DIGITO_STB;
wire PIN_INCORRECTO;
wire TIPO_TRANS;
wire [31:0] MONTO;
wire MONTO_STB;
wire BALANCE_ACTUALIZADO;
wire ENTREGAR_DINERO;
wire FONDOS_INSUFICIENTES;
wire ADVERTENCIA;
wire BLOQUEO;

initial begin
  $dumpfile("testbench.vcd"); //Genera un archivo vcd 
  $dumpvars; //Se utilizan todas las variable
end

// Instanciar el módulo ATMController
    controller U0 (
        .CLK(CLK),
        .RESET(RESET),
        .TARJETA_RECIBIDA(TARJETA_RECIBIDA),
        .PIN(PIN),
        .DIGITO(DIGITO),
        .DIGITO_STB(DIGITO_STB),
        .PIN_INCORRECTO(PIN_INCORRECTO),
        .TIPO_TRANS(TIPO_TRANS),
        .MONTO(MONTO),
        .MONTO_STB(MONTO_STB),
        .BALANCE_ACTUALIZADO(BALANCE_ACTUALIZADO),
        .ENTREGAR_DINERO(ENTREGAR_DINERO),
        .FONDOS_INSUFICIENTES(FONDOS_INSUFICIENTES),
        .ADVERTENCIA(ADVERTENCIA),
        .BLOQUEO(BLOQUEO)
    );


// Instanciar el módulo ATMController
    tester P0 (
        .CLK(CLK),
        .RESET(RESET),
        .TARJETA_RECIBIDA(TARJETA_RECIBIDA),
        .PIN(PIN),
        .DIGITO(DIGITO),
        .DIGITO_STB(DIGITO_STB),
        .PIN_INCORRECTO(PIN_INCORRECTO),
        .TIPO_TRANS(TIPO_TRANS),
        .MONTO(MONTO),
        .MONTO_STB(MONTO_STB),
        .BALANCE_ACTUALIZADO(BALANCE_ACTUALIZADO),
        .ENTREGAR_DINERO(ENTREGAR_DINERO),
        .FONDOS_INSUFICIENTES(FONDOS_INSUFICIENTES),
        .ADVERTENCIA(ADVERTENCIA),
        .BLOQUEO(BLOQUEO)
    );


endmodule

TAREA3/conductual_version/testbench.vcd
$date
	Sat May 18 21:49:25 2024
$end
$version
	Icarus Verilog
$end
$timescale
	1s
$end
$scope module controller_tb $end
$var wire 1 ! TIPO_TRANS $end
$var wire 1 " TARJETA_RECIBIDA $end
$var wire 1 # RESET $end
$var wire 1 $ PIN_INCORRECTO $end
$var wire 16 % PIN [15:0] $end
$var wire 1 & MONTO_STB $end
$var wire 32 ' MONTO [31:0] $end
$var wire 1 ( FONDOS_INSUFICIENTES $end
$var wire 1 ) ENTREGAR_DINERO $end
$var wire 1 * DIGITO_STB $end
$var wire 4 + DIGITO [3:0] $end
$var wire 1 , CLK $end
$var wire 1 - BLOQUEO $end
$var wire 1 . BALANCE_ACTUALIZADO $end
$var wire 1 / ADVERTENCIA $end
$scope module P0 $end
$var wire 1 $ PIN_INCORRECTO $end
$var wire 1 ( FONDOS_INSUFICIENTES $end
$var wire 1 ) ENTREGAR_DINERO $end
$var wire 1 - BLOQUEO $end
$var wire 1 . BALANCE_ACTUALIZADO $end
$var wire 1 / ADVERTENCIA $end
$var reg 1 , CLK $end
$var reg 4 0 DIGITO [3:0] $end
$var reg 1 * DIGITO_STB $end
$var reg 32 1 MONTO [31:0] $end
$var reg 1 & MONTO_STB $end
$var reg 16 2 PIN [15:0] $end
$var reg 1 # RESET $end
$var reg 1 " TARJETA_RECIBIDA $end
$var reg 1 ! TIPO_TRANS $end
$upscope $end
$scope module U0 $end
$var wire 1 , CLK $end
$var wire 4 3 DIGITO [3:0] $end
$var wire 1 * DIGITO_STB $end
$var wire 32 4 MONTO [31:0] $end
$var wire 1 & MONTO_STB $end
$var wire 16 5 PIN [15:0] $end
$var wire 1 # RESET $end
$var wire 1 " TARJETA_RECIBIDA $end
$var wire 1 ! TIPO_TRANS $end
$var reg 1 / ADVERTENCIA $end
$var reg 64 6 BALANCE [63:0] $end
$var reg 1 . BALANCE_ACTUALIZADO $end
$var reg 1 - BLOQUEO $end
$var reg 1 ) ENTREGAR_DINERO $end
$var reg 1 ( FONDOS_INSUFICIENTES $end
$var reg 2 7 INTENTOS [1:0] $end
$var reg 64 8 MONTO_ext [63:0] $end
$var reg 1 $ PIN_INCORRECTO $end
$var reg 3 9 contador_digitos [2:0] $end
$var reg 4 : estado_actual [3:0] $end
$var reg 2 ; nxt_INTENTOS [1:0] $end
$var reg 3 < nxt_contador_digitos [2:0] $end
$var reg 16 = pin_interno [15:0] $end
$var reg 4 > proximo_estado [3:0] $end
$upscope $end
$upscope $end
$enddefinitions $end
#0
$dumpvars
b0 >
bx =
bx <
bx ;
bx :
bx 9
bx 8
bx 7
bx 6
bx 5
bx 4
bx 3
bx 2
bx 1
bx 0
0/
0.
0-
0,
bx +
0*
0)
0(
bx '
0&
bx %
0$
0#
0"
0!
$end
#5
b0 8
b0 ;
b0 <
b0 9
b0 7
b0 =
b0 :
1,
#10
0,
#15
1,
#20
0,
1#
#25
b1 :
b1 >
1,
1"
#30
0,
#35
1,
b11010001110011 %
b11010001110011 2
b11010001110011 5
#40
0,
#45
1,
#50
0,
#55
b1 =
b1 9
b10 <
1,
b1 +
b1 0
b1 3
1*
#60
0,
#65
b1 <
1,
0*
#70
0,
#75
b10011 =
b10 9
b11 <
1,
b11 +
b11 0
b11 3
1*
#80
0,
#85
b10 <
1,
0*
#90
0,
#95
b100110111 =
b11 9
b100 <
1,
b111 +
b111 0
b111 3
1*
#100
0,
#105
b11 <
1,
0*
#110
0,
#115
b10 >
b1 ;
b1001101111000 =
b100 9
b0 <
1,
b1000 +
b1000 0
b1000 3
1*
#120
0,
#125
1$
b1 7
b0 9
b10 :
b1 ;
b0 <
b1 >
1,
0*
#130
0,
#135
0$
b1 :
1,
#140
0,
#145
b11011110000001 =
b1 9
b10 <
1,
b1 +
b1 0
b1 3
1*
#150
0,
#155
b1 <
1,
0*
#160
0,
#165
b111100000010011 =
b10 9
b11 <
1,
b11 +
b11 0
b11 3
1*
#170
0,
#175
b10 <
1,
0*
#180
0,
#185
b1000000100110111 =
b11 9
b100 <
1,
b111 +
b111 0
b111 3
1*
#190
0,
#195
b11 <
1,
0*
#200
0,
#205
b10 >
b10 ;
b1001101111000 =
b100 9
b0 <
1,
b1000 +
b1000 0
b1000 3
1*
#210
0,
#215
1/
1$
b10 7
b0 9
b10 :
b10 ;
b0 <
b1 >
1,
0*
#220
0,
#225
0/
0$
b1 :
1,
#230
0,
#235
b11011110000001 =
b1 9
b10 <
1,
b1 +
b1 0
b1 3
1*
#240
0,
#245
b1 <
1,
0*
#250
0,
#255
b111100000010011 =
b10 9
b11 <
1,
b11 +
b11 0
b11 3
1*
#260
0,
#265
b10 <
1,
0*
#270
0,
#275
b1000000100110111 =
b11 9
b100 <
1,
b111 +
b111 0
b111 3
1*
#280
0,
#285
b11 <
1,
0*
#290
0,
#295
b10 >
b11 ;
b1001101111000 =
b100 9
b0 <
1,
b1000 +
b1000 0
b1000 3
1*
#300
0,
#305
1$
b11 7
b0 9
b10 :
b11 ;
b0 <
b110 >
1,
0*
#310
0,
#315
1-
b110 :
0$
b110 >
1,
0"
#320
0,
#325
1,
b0 +
b0 0
b0 3
#330
0,
#335
1,
#340
0,
#345
b0 ;
b0 7
b0 =
b0 :
b0 >
0-
1,
0#
#350
0,
#355
1,
1#
#360
0,
#365
b1 :
b1 >
1,
1"
#370
0,
#375
1,
#380
0,
#385
b11 =
b1 9
b10 <
1,
1*
b11 +
b11 0
b11 3
#390
0,
#395
b1 <
1,
0*
#400
0,
#405
b110100 =
b10 9
b11 <
1,
1*
b100 +
b100 0
b100 3
#410
0,
#415
b10 <
1,
0*
#420
0,
#425
b1101000111 =
b11 9
b100 <
1,
1*
b111 +
b111 0
b111 3
#430
0,
#435
b11 <
1,
0*
#440
0,
#445
b10 >
b1 ;
b11010001110011 =
b100 9
b0 <
1,
1*
b11 +
b11 0
b11 3
#450
0,
#455
b1 7
b0 9
b10 :
b1 ;
b0 <
b11 >
1,
0*
#460
0,
#465
b1001110001000 6
b11 :
1,
#470
0,
#475
1.
b1101101011000 6
b100 :
b100 >
1,
1&
b11111010000 '
b11111010000 1
b11111010000 4
#480
0,
#485
1.
1,
b0 '
b0 1
b0 4
0&
#490
0,
#495
b0 ;
b0 :
b0 >
0.
1,
0"
#500
0,
#505
b0 7
1,
b0 +
b0 0
b0 3
#510
0,
#515
b1 :
b1 >
1,
1"
#520
0,
#525
1,
#530
0,
#535
b100011100110001 =
b1 9
b10 <
1,
b1 +
b1 0
b1 3
1*
#540
0,
#545
b1 <
1,
0*
#550
0,
#555
b111001100010011 =
b10 9
b11 <
1,
b11 +
b11 0
b11 3
1*
#560
0,
#565
b10 <
1,
0*
#570
0,
#575
b11000100110111 =
b11 9
b100 <
1,
b111 +
b111 0
b111 3
1*
#580
0,
#585
b11 <
1,
0*
#590
0,
#595
b10 >
b1 ;
b1001101111000 =
b100 9
b0 <
1,
b1000 +
b1000 0
b1000 3
1*
#600
0,
#605
1$
b1 7
b0 9
b10 :
b1 ;
b0 <
b1 >
1,
0*
#610
0,
#615
0$
b1 :
1,
#620
0,
#625
b11011110000001 =
b1 9
b10 <
1,
b1 +
b1 0
b1 3
1*
#630
0,
#635
b1 <
1,
0*
#640
0,
#645
b111100000010011 =
b10 9
b11 <
1,
b11 +
b11 0
b11 3
1*
#650
0,
#655
b10 <
1,
0*
#660
0,
#665
b1000000100110111 =
b11 9
b100 <
1,
b111 +
b111 0
b111 3
1*
#670
0,
#675
b11 <
1,
0*
#680
0,
#685
b10 >
b10 ;
b1001101111000 =
b100 9
b0 <
1,
b1000 +
b1000 0
b1000 3
1*
#690
0,
#695
1/
1$
b10 7
b0 9
b10 :
b10 ;
b0 <
b1 >
1,
0*
#700
0,
#705
0/
0$
b1 :
1,
#710
0,
#715
b11011110000011 =
b1 9
b10 <
1,
1*
b11 +
b11 0
b11 3
#720
0,
#725
b1 <
1,
0*
#730
0,
#735
b111100000110100 =
b10 9
b11 <
1,
1*
b100 +
b100 0
b100 3
#740
0,
#745
b10 <
1,
0*
#750
0,
#755
b1000001101000111 =
b11 9
b100 <
1,
1*
b111 +
b111 0
b111 3
#760
0,
#765
b11 <
1,
0*
#770
0,
#775
b10 >
b11 ;
b11010001110011 =
b100 9
b0 <
1,
1*
b11 +
b11 0
b11 3
#780
0,
#785
b11 7
b0 9
b10 :
b11 ;
b0 <
b11 >
1,
0*
#790
0,
#795
b1001110001000 6
b11 :
b11 >
1,
1!
#800
0,
#805
1.
1)
b101110111000 6
b101 :
b101 >
b0 8
1,
1&
b11111010000 '
b11111010000 1
b11111010000 4
#810
0,
#815
b0 ;
b0 :
b0 >
0)
0.
1,
0"
0&
#820
0,
#825
b0 7
1,
b0 +
b0 0
b0 3
#830
0,
#835
b1 :
b1 >
1,
1"
#840
0,
#845
1,
#850
0,
#855
b100011100110011 =
b1 9
b10 <
1,
1*
b11 +
b11 0
b11 3
#860
0,
#865
b1 <
1,
0*
#870
0,
#875
b111001100110100 =
b10 9
b11 <
1,
1*
b100 +
b100 0
b100 3
#880
0,
#885
b10 <
1,
0*
#890
0,
#895
b11001101000111 =
b11 9
b100 <
1,
1*
b111 +
b111 0
b111 3
#900
0,
#905
b11 <
1,
0*
#910
0,
#915
b10 >
b1 ;
b11010001110011 =
b100 9
b0 <
1,
1*
b11 +
b11 0
b11 3
#920
0,
#925
b1 7
b0 9
b10 :
b1 ;
b0 <
b11 >
1,
0*
#930
0,
#935
b1001110001000 6
b11 :
1,
#940
0,
#945
1(
b10011100010000 8
1,
1&
b10011100010000 '
b10011100010000 1
b10011100010000 4
#950
0,
#955
b0 8
b0 ;
b0 :
b0 >
0(
1,
0&
0"
#960
0,
#965
b0 7
1,
b0 +
b0 0
b0 3
