TAREA4/DC_configuration/tester.v
module tester( 
//inputs
MOSI,
SCK,
CS,
//outputs
MISO,
clk,
reset, 
CKP,
CPH
);


output clk, reset, CKP, CPH; // Las salidas de este módulo son las entradas que le llegarán al generador
output MISO;
input MOSI;
input SCK;
input CS;


reg clk, reset, CKP, CPH; // Las salidas de este módulo son las entradas que le llegarán al generador

wire MISO;
wire MOSI;
wire SCK;
wire CS;

// Secuencia de pruebas 
initial begin
    // Inicialización
   	clk = 0;
   	CKP = 0;
    CPH = 0;
    reset = 0;
	#40 reset = 1;
    // Initialize inputs
        
    // Test mode 0 (CPOL=0, CPHA=0)
    CKP = 0;
    CPH = 0;
    
    #725; // Wait for 8 clock cycles (80 time units at clk period of 10)
    
    // Test mode 0 (CPOL=0, CPHA=0)
    
    CKP = 0;
    CPH = 1;
    
    #640; // Wait for 8 clock cycles (80 time units at clk period of 10)

    // Test mode 0 (CPOL=0, CPHA=0)
    CKP = 1;
    CPH = 0;
    #700; // Wait for 8 clock cycles
    
    // Test mode 0 (CPOL=0, CPHA=0)
    CKP = 1;
    CPH = 1;
    
    #2000; // Wait for 8 clock cycles
    $finish;
end

always begin
 #5 clk = !clk;
end
endmodule

TAREA4/DC_configuration/objetivo.v
module receptor_spi(
    // Inputs
    input wire SS,       // Chip Select
    input wire SCK,      // Serial Clock
    input wire MOSI,     // Master Output Slave Input
    input wire reset,    // Reset signal
    input wire CKP,      // Clock Polarity
    input wire CPH,      // Clock Phase
    // Outputs
    output reg MISO      // Master Input Slave Output
);
   
 // Declaración de registros internos y parámetros
    reg [2:0] estado_actual, proximo_estado;
    reg [4:0] contador_bits_obj, prox_contador_bits_obj;
    reg [15:0] current_data_obj = 16'b0000011100000011; // Inicializar con la data a enviar desde el periferico
    reg [4:0] bit_index;
    reg last_data_sent; // Registro para rastrear la data enviada
    reg [3:0] trans_done; // Registro para indicar que se han enviado 
    reg [15:0] sampled_data_MOSI;
    
    
     // Definición de estados
    parameter IDLE = 3'b000;
    parameter VERIFICACION = 3'b001;
    parameter ENVIO_DATOS = 3'b010;
    parameter FINALIZACION_ENVIO = 3'b011;
    parameter INICIALIZACION = 3'b100;
    // Parámetro para el número de bits en la transacción SPI
    parameter NUM_BITS = 15;

    // Lógica secuencial para el envío de datos utilizando SCK (flanco positivo)
    always @(posedge SCK or negedge reset) begin
        if (!reset) begin
            estado_actual <= 0;
            MISO <= 1'b0;
            sampled_data_MOSI <= 0;
            bit_index <= 0;
            trans_done <= 0;
            last_data_sent <= 0;
        end else begin
            estado_actual <= proximo_estado;
            contador_bits_obj <= prox_contador_bits_obj;
            sampled_data_MOSI <= (sampled_data_MOSI << 1) | MOSI;
            if (!SS && estado_actual == 2 && contador_bits_obj < NUM_BITS) begin 
                // Envío de datos en el flanco positivo de SCK
                //sampled_data_MISO <= {sampled_data_MISO[6:0], MISO};
                if ((!CPH && !CKP) || (CPH && CKP)) begin
                    // MOSI toma el bit correspondiente de izquierda a derecha (MSB a LSB)
                    MISO <= current_data_obj[NUM_BITS - bit_index - 1];
                    bit_index <= bit_index + 1;
                    contador_bits_obj <= contador_bits_obj + 1;
                    //last_data_sent = 1;
                end

            end else begin
                // Finalizar la transacción cuando se hayan enviado todos los bits
                bit_index <= 0;
                //contador_bits_master <= 0;
                last_data_sent = 0;
            
            end
        end
    end

    // Lógica secuencial para el envío de datos utilizando SCK (flanco negativo)
    always @(negedge SCK or negedge reset) begin
        if (!reset) begin
            estado_actual <= 0;
            contador_bits_obj <= 0;
            bit_index <= 0;
        end else begin
            contador_bits_obj <= prox_contador_bits_obj;
            //CS <= 0;

            if (estado_actual == 2 && contador_bits_obj < NUM_BITS) begin
                // Envío de datos en el flanco positivo de SCK
                if ((CPH && !CKP) || (!CPH && CKP)) begin
                    // MOSI toma el bit correspondiente de izquierda a derecha (MSB a LSB)
                    MISO <= current_data_obj[NUM_BITS - bit_index - 1];
                    bit_index <= bit_index + 1;
                    contador_bits_obj <= contador_bits_obj + 1;
                    //last_data_sent = 1;
                    if (estado_actual == 3) MISO <= 0;
                end
            end else begin
                // Finalizar la transacción cuando se hayan enviado todos los bits
                //MOSI <= 1'b0;
                bit_index <= 0;
                //contador_bits_master <= 0;
                //CS <= 1;
            end
        end
    end

   // Lógica combinacional
    always @(*) begin
        // Mantener el valor actual por defecto
        proximo_estado = estado_actual;
        prox_contador_bits_obj = contador_bits_obj;

        // Definir el comportamiento basado en el estado actual
        case (estado_actual)
            IDLE: begin
               
                if (trans_done < 4) begin // Numero de trans se puede ir variando para la simulacion
                   proximo_estado = VERIFICACION;
                end
            end
             VERIFICACION: begin
                if (!SS) proximo_estado = ENVIO_DATOS; // Utiliza la señal de entrada desde el master como condición para poder enviar datos

            end

            ENVIO_DATOS: begin
            // Estado de envío de data
            
            if (contador_bits_obj <= 14) begin
                proximo_estado = ENVIO_DATOS; // Continuar enviando bits
            end 
        
            else begin
                proximo_estado = FINALIZACION_ENVIO; // Se deja de enviar data cuando se manden los bits respectivos
            end
            end

           FINALIZACION_ENVIO: begin
            // Estado de finalización de envío
            if ((!CPH && !CKP) || (CPH && CKP)) MISO <= 0;
            //if ((CPH && !CKP) || (!CPH && CKP)) MISO <= 0;

            proximo_estado = INICIALIZACION; // Ir al estado de inicialización
            
            end
            INICIALIZACION: begin   // Estado de inicialización para corrobar el valor de la señal y reestablecer las variables auxiliares
                MISO <= 0;
                //CS <= 1;
                sampled_data_MOSI <= 0;
                proximo_estado = IDLE;
                contador_bits_obj <= 0;
            end 
            default: begin
                // Estado por defecto
                proximo_estado = IDLE;
            end
        endcase
    end

endmodule

TAREA4/SPI/generador.v
module generador_spi(
   // Outputs
    output reg MOSI,
    output reg CS,
    output SCK,
    // Inputs
    input wire MISO,
    input wire clk,
    input wire reset, 
    input wire CKP,
    input wire CPH
);
  
    // Declaración de registros internos y parámetros
    localparam DIV_FREQ = 2; // Para hacerlo al 25% de CLK
    reg [2:0] estado_actual, proximo_estado;
    reg [4:0] contador_bits_master, prox_contador_bits_master;
    reg [DIV_FREQ-1:0] div_freq;
    reg sck_reg;
    reg [15:0] current_data; // Registro de datos actuales a enviar
    reg [4:0] bit_index;
    reg last_data_sent; // Registro para rastrear el último dato enviado
    reg [3:0] trans_done; // Registro para indicar que se han enviado la data
    reg [15:0] sampled_data_MISO;
    
    // Definición de estados
    parameter IDLE = 3'b000;
    parameter VERIFICACION = 3'b001;
    parameter ENVIO_DATOS = 3'b010;
    parameter FINALIZACION_ENVIO = 3'b011;
    parameter INICIALIZACION = 3'b100;
    
    // Asignación para crear el reloj a una frecuencia menor
    assign SCK = sck_reg;

    // Lógica secuencial para generar SCK
    always @(posedge clk or negedge reset) begin
        if (!reset) begin
            // Reiniciar valores del estado y contadores
            current_data <= 16'b0000001100000100; // Inicializar con esta data
            div_freq <= 0;
            sck_reg <= CKP; // Configurar la polaridad del reloj
            last_data_sent <= 0;
            sampled_data_MISO <= 0;
            contador_bits_master <= 0;
        end else begin
            div_freq <= div_freq + 1;
            if (div_freq == (DIV_FREQ - 1)) begin
                sck_reg <= ~sck_reg; // Generar SCK al 25% de la frecuencia del clk
                div_freq <= 0;
            end
             // Mantener la polaridad del reloj cuando no hay transacción
            if (CS) begin
                sck_reg <= CKP; // Mantener el estado de reposo especificado por CKP
            end
        end
    end
    // Parámetro para el número de bits en la transacción SPI
    parameter NUM_BITS = 15;

    // Lógica secuencial para el envío de datos utilizando SCK (flanco positivo)
    always @(posedge SCK or negedge reset) begin
        if (!reset) begin
            estado_actual <= 0;
            MOSI <= 1'b0;
            //current_data <= 0; // Inicializar con data1
            CS <= 0;
            bit_index <= 0;
            trans_done <= 0;
            last_data_sent <= 0;
        end else begin
            estado_actual <= proximo_estado;
            contador_bits_master <= prox_contador_bits_master;
           
            if (estado_actual == 4) begin
                trans_done <= trans_done + 1;
            end
           
            sampled_data_MISO <= (sampled_data_MISO << 1) | MISO;
            if (estado_actual == 2 && contador_bits_master < NUM_BITS) begin
                // Envío de datos en el flanco positivo de SCK
                //sampled_data_MISO <= {sampled_data_MISO[6:0], MISO};
                if ((!CPH && !CKP) || (CPH && CKP)) begin
                    // MOSI toma el bit correspondiente de izquierda a derecha (MSB a LSB)
                    MOSI <= current_data[NUM_BITS - bit_index - 1];
                    bit_index <= bit_index + 1;
                    contador_bits_master <= contador_bits_master + 1;
                end

            end else begin
                // Finalizar la transacción cuando se hayan enviado todos los bits
                //MOSI <= 1'b0;
                bit_index <= 0;
                //CS <= 1;
                //contador_bits_master <= 0;
                last_data_sent = 0;
            
            end
        end
    end


    // Lógica secuencial para el envío de datos utilizando SCK (flanco negativo)
    always @(negedge SCK or negedge reset) begin
        if (!reset) begin
            estado_actual <= 0;
            contador_bits_master <= 0;
            MOSI <= 1'b0;
            //current_data <= 0; // Inicializar con data1
            bit_index <= 0;
        end else begin
            contador_bits_master <= prox_contador_bits_master;
        
            if (estado_actual == 2 && contador_bits_master < NUM_BITS) begin
                // Envío de datos en el flanco negativo de SCK
                if ((CPH && !CKP) || (!CPH && CKP)) begin
                    // MOSI toma el bit correspondiente de izquierda a derecha (MSB a LSB)
                    MOSI <= current_data[NUM_BITS - bit_index - 1];
                    bit_index <= bit_index + 1;
                    contador_bits_master <= contador_bits_master + 1;
                    //last_data_sent = 1;
                end
            end else begin
                // Finalizar la transacción cuando se hayan enviado todos los bits
                //MOSI <= 1'b0;
                bit_index <= 0;
                //contador_bits_master <= 0;
                //CS <= 1;
            end
        end
    end

   // Lógica combinacional
    always @(*) begin
        // Mantener el valor actual por defecto
        proximo_estado = estado_actual;
        prox_contador_bits_master = contador_bits_master;

        // Definir el comportamiento basado en el estado actual
        case (estado_actual)
            IDLE: begin
                // Estado de reposo
                CS = 1;
                if (trans_done < 4) begin // Numero de trans se puede ir variando para la simulacion
                   proximo_estado = VERIFICACION;
                end    
            end

            VERIFICACION: begin // Verificamos si se activa el chip select para enviar data
            	CS = 0;
                if (!CS) proximo_estado = ENVIO_DATOS;

            end

            ENVIO_DATOS: begin
            // Estado de envío de data1 o data2
            if(trans_done == 4) CS <= 1;
            
            if (contador_bits_master <= 14) begin // Se envia bit a bit utilizando cada flanco respectivo
                proximo_estado = ENVIO_DATOS; // Continuar enviando bits
            end 
        
            else begin
                proximo_estado = FINALIZACION_ENVIO; // Finalizar la transacción
            end
            end

           FINALIZACION_ENVIO: begin
            // Estado de finalización de envío para corroborar que MOSI no siga enviando datos
            if ((!CPH && !CKP) || (CPH && CKP)) MOSI <= 0;
            
            //CS = 1;
            proximo_estado = INICIALIZACION; // Ir al estado de inicialización
       
            end
            INICIALIZACION: begin   // En este estado inicializamos y manejamos la señal de chip select para que no siga enviando datos
               	CS = 1;
                sampled_data_MISO <= 0;
                proximo_estado = IDLE;
                contador_bits_master <= 0;

            end 
            default: begin
                // Estado por defecto
                proximo_estado = IDLE;
            end
        endcase
    end


endmodule

TAREA4/DC_configuration/testbench.v
`include "generador.v"
`include "tester.v"
`include "objetivo.v"

module generador_tb;
wire clk;
wire reset;
wire MISO;
wire MOSI;
wire MOSI_MOSI;
wire MISO_MOSI;
wire MISO_MISO;
wire SCK;
wire CS;
wire CKP;
wire CPH;

initial begin
  $dumpfile("testbench.vcd"); //Genera un archivo vcd 
  $dumpvars; //Se utilizan todas las variable
end


// Instanciar el módulo master
    generador_spi U0 (
        .clk(clk),
        .reset(reset),
        .MOSI(MOSI_MOSI),
        .SCK(SCK),
        .CS(CS),
        .MISO(MISO_MISO),
        .CKP(CKP),
        .CPH(CPH)
    );

// Instanciar el módulo objetivo 1

    receptor_spi U1 (
        .reset(reset),
        .MOSI(MOSI_MOSI),
        .SCK(SCK),
        .SS(CS),
        .MISO(MISO_MOSI),
        .CKP(CKP),
        .CPH(CPH)
        
    );
    
    // Instanciar el módulo objetivo 2

    	receptor_spi U2 (
        .reset(reset),
        .MOSI(MISO_MOSI),
        .SCK(SCK),
        .SS(CS),
        .MISO(MISO_MISO),
        .CKP(CKP),
        .CPH(CPH)
        
    );

// Instanciar el módulo ATMController
    tester P0 (
       .clk(clk),
        .reset(reset),
        .MOSI(MOSI),
        .SCK(SCK),
        .CS(CS),
        .MISO(MISO),
        .CKP(CKP),
        .CPH(CPH)
    );


endmodule

TAREA4/DC_configuration/testbench.vcd
$date
	Sat Jun  1 20:17:38 2024
$end
$version
	Icarus Verilog
$end
$timescale
	1s
$end
$scope module generador_tb $end
$var wire 1 ! MISO $end
$var wire 1 " MOSI $end
$var wire 1 # reset $end
$var wire 1 $ clk $end
$var wire 1 % SCK $end
$var wire 1 & MOSI_MOSI $end
$var wire 1 ' MISO_MOSI $end
$var wire 1 ( MISO_MISO $end
$var wire 1 ) CS $end
$var wire 1 * CPH $end
$var wire 1 + CKP $end
$scope module P0 $end
$var wire 1 ! MISO $end
$var wire 1 " MOSI $end
$var wire 1 % SCK $end
$var wire 1 ) CS $end
$var reg 1 + CKP $end
$var reg 1 * CPH $end
$var reg 1 $ clk $end
$var reg 1 # reset $end
$upscope $end
$scope module U0 $end
$var wire 1 + CKP $end
$var wire 1 * CPH $end
$var wire 1 % SCK $end
$var wire 1 $ clk $end
$var wire 1 # reset $end
$var wire 1 ( MISO $end
$var reg 1 ) CS $end
$var reg 1 & MOSI $end
$var reg 5 , bit_index [4:0] $end
$var reg 5 - contador_bits_master [4:0] $end
$var reg 16 . current_data [15:0] $end
$var reg 2 / div_freq [1:0] $end
$var reg 3 0 estado_actual [2:0] $end
$var reg 1 1 last_data_sent $end
$var reg 5 2 prox_contador_bits_master [4:0] $end
$var reg 3 3 proximo_estado [2:0] $end
$var reg 16 4 sampled_data_MISO [15:0] $end
$var reg 1 5 sck_reg $end
$var reg 4 6 trans_done [3:0] $end
$upscope $end
$scope module U1 $end
$var wire 1 + CKP $end
$var wire 1 * CPH $end
$var wire 1 & MOSI $end
$var wire 1 % SCK $end
$var wire 1 ) SS $end
$var wire 1 # reset $end
$var reg 1 ' MISO $end
$var reg 5 7 bit_index [4:0] $end
$var reg 5 8 contador_bits_obj [4:0] $end
$var reg 16 9 current_data_obj [15:0] $end
$var reg 3 : estado_actual [2:0] $end
$var reg 1 ; last_data_sent $end
$var reg 5 < prox_contador_bits_obj [4:0] $end
$var reg 3 = proximo_estado [2:0] $end
$var reg 16 > sampled_data_MOSI [15:0] $end
$var reg 4 ? trans_done [3:0] $end
$upscope $end
$scope module U2 $end
$var wire 1 + CKP $end
$var wire 1 * CPH $end
$var wire 1 ' MOSI $end
$var wire 1 % SCK $end
$var wire 1 ) SS $end
$var wire 1 # reset $end
$var reg 1 ( MISO $end
$var reg 5 @ bit_index [4:0] $end
$var reg 5 A contador_bits_obj [4:0] $end
$var reg 16 B current_data_obj [15:0] $end
$var reg 3 C estado_actual [2:0] $end
$var reg 1 D last_data_sent $end
$var reg 5 E prox_contador_bits_obj [4:0] $end
$var reg 3 F proximo_estado [2:0] $end
$var reg 16 G sampled_data_MOSI [15:0] $end
$var reg 4 H trans_done [3:0] $end
$upscope $end
$upscope $end
$enddefinitions $end
#0
$dumpvars
b0 H
b0 G
b1 F
b0 E
0D
b0 C
b11100000011 B
b0 A
b0 @
b0 ?
b0 >
b1 =
b0 <
0;
b0 :
b11100000011 9
b0 8
b0 7
b0 6
05
b0 4
b1 3
b0 2
01
b0 0
b0 /
b1100000100 .
b0 -
b0 ,
0+
0*
1)
0(
0'
0&
0%
0$
0#
z"
z!
$end
#5
1$
#10
0$
#15
1$
#20
0$
#25
1$
#30
0$
#35
1$
#40
0$
1#
#45
b1 /
1$
#50
0$
#55
b10 F
b10 =
b10 3
0)
b1 C
b1 :
b1 0
0%
05
b0 /
1$
#60
0$
#65
b1 /
1$
#70
0$
#75
b10 0
b10 :
b10 C
1%
15
b0 /
1$
#80
0$
#85
b1 /
1$
#90
0$
#95
0%
05
b0 /
1$
#100
0$
#105
b1 /
1$
#110
0$
#115
b1 E
b1 <
b1 2
b1 A
b1 @
b1 8
b1 7
b1 -
b1 ,
1%
15
b0 /
1$
#120
0$
#125
b1 /
1$
#130
0$
#135
0%
05
b0 /
1$
#140
0$
#145
b1 /
1$
#150
0$
#155
b10 2
b10 <
b10 E
b10 -
b10 ,
b10 8
b10 7
b10 A
b10 @
1%
15
b0 /
1$
#160
0$
#165
b1 /
1$
#170
0$
#175
0%
05
b0 /
1$
#180
0$
#185
b1 /
1$
#190
0$
#195
b11 E
b11 <
b11 2
b11 A
b11 @
b11 8
b11 7
b11 -
b11 ,
1%
15
b0 /
1$
#200
0$
#205
b1 /
1$
#210
0$
#215
0%
05
b0 /
1$
#220
0$
#225
b1 /
1$
#230
0$
#235
b100 2
b100 <
b100 E
b100 -
b100 ,
b100 8
b100 7
b100 A
b100 @
1%
15
b0 /
1$
#240
0$
#245
b1 /
1$
#250
0$
#255
0%
05
b0 /
1$
#260
0$
#265
b1 /
1$
#270
0$
#275
b101 E
b101 <
b101 2
b101 A
b101 @
1(
b101 8
b101 7
1'
b101 -
b101 ,
1%
15
b0 /
1$
#280
0$
#285
b1 /
1$
#290
0$
#295
0%
05
b0 /
1$
#300
0$
#305
b1 /
1$
#310
0$
#315
b110 2
b110 <
b110 E
b110 -
b110 ,
1&
b1 4
b110 8
b110 7
b110 A
b110 @
b1 G
1%
15
b0 /
1$
#320
0$
#325
b1 /
1$
#330
0$
#335
0%
05
b0 /
1$
#340
0$
#345
b1 /
1$
#350
0$
#355
b111 E
b111 <
b111 2
b111 A
b111 @
b11 G
b111 8
b111 7
b1 >
b111 -
b111 ,
b11 4
1%
15
b0 /
1$
#360
0$
#365
b1 /
1$
#370
0$
#375
0%
05
b0 /
1$
#380
0$
#385
b1 /
1$
#390
0$
#395
b1000 2
b1000 <
b1000 E
b1000 -
b1000 ,
0&
b111 4
b1000 8
b1000 7
0'
b11 >
b1000 A
b1000 @
0(
b111 G
1%
15
b0 /
1$
#400
0$
#405
b1 /
1$
#410
0$
#415
0%
05
b0 /
1$
#420
0$
#425
b1 /
1$
#430
0$
#435
b1001 E
b1001 <
b1001 2
b1001 A
b1001 @
b1110 G
b1001 8
b1001 7
b110 >
b1001 -
b1001 ,
b1110 4
1%
15
b0 /
1$
#440
0$
#445
b1 /
1$
#450
0$
#455
0%
05
b0 /
1$
#460
0$
#465
b1 /
1$
#470
0$
#475
b1010 2
b1010 <
b1010 E
b1010 -
b1010 ,
b11100 4
b1010 8
b1010 7
b1100 >
b1010 A
b1010 @
b11100 G
1%
15
b0 /
1$
#480
0$
#485
b1 /
1$
#490
0$
#495
0%
05
b0 /
1$
#500
0$
#505
b1 /
1$
#510
0$
#515
b1011 E
b1011 <
b1011 2
b1011 A
b1011 @
b111000 G
b1011 8
b1011 7
b11000 >
b1011 -
b1011 ,
b111000 4
1%
15
b0 /
1$
#520
0$
#525
b1 /
1$
#530
0$
#535
0%
05
b0 /
1$
#540
0$
#545
b1 /
1$
#550
0$
#555
b1100 2
b1100 <
b1100 E
b1100 -
b1100 ,
b1110000 4
b1100 8
b1100 7
b110000 >
b1100 A
b1100 @
b1110000 G
1%
15
b0 /
1$
#560
0$
#565
b1 /
1$
#570
0$
#575
0%
05
b0 /
1$
#580
0$
#585
b1 /
1$
#590
0$
#595
b1101 E
b1101 <
b1101 2
b1101 A
b1101 @
b11100000 G
b1101 8
b1101 7
b1100000 >
b1101 -
b1101 ,
1&
b11100000 4
1%
15
b0 /
1$
#600
0$
#605
b1 /
1$
#610
0$
#615
0%
05
b0 /
1$
#620
0$
#625
b1 /
1$
#630
0$
#635
b1110 2
b1110 <
b1110 E
b1110 -
b1110 ,
0&
b111000000 4
b1110 8
b1110 7
1'
b11000001 >
b1110 A
b1110 @
1(
b111000000 G
1%
15
b0 /
1$
#640
0$
#645
b1 /
1$
#650
0$
#655
0%
05
b0 /
1$
#660
0$
#665
b1 /
1$
#670
0$
#675
b11 F
b1111 E
b11 =
b1111 <
b11 3
b1111 2
b1111 A
b1111 @
b1110000001 G
b1111 8
b1111 7
b110000010 >
b1111 -
b1111 ,
b1110000001 4
1%
15
b0 /
1$
#680
0$
#685
b1 /
1$
#690
0$
#695
b0 ,
b0 7
b0 @
0%
05
b0 /
1$
#700
0$
#705
b1 /
1$
#710
0$
#715
0'
0(
b100 3
b100 =
b100 F
b11100000011 4
b11 0
b1100000100 >
b11 :
b11100000011 G
b11 C
1%
15
b0 /
1$
#720
0$
#725
b1 /
1$
#730
0$
#735
0%
05
b0 /
1$
#740
0$
#745
b1 /
1$
#750
0$
#755
b0 E
b0 <
b0 2
b0 A
b0 8
b0 -
b0 F
b0 =
b0 3
1)
b0 G
b100 C
b0 >
b100 :
b0 4
b100 0
1%
15
b0 /
1$
#760
0$
#765
0%
05
b1 /
b0 3
b0 =
b0 F
1$
1*
#770
0$
#775
b1 3
b1 =
b1 F
b1 6
b0 0
b0 :
b0 C
0%
05
b0 /
1$
#780
0$
#785
b1 /
1$
#790
0$
#795
b10 F
b10 =
b10 3
0)
b1 C
b1 :
b1 0
0%
05
b0 /
1$
#800
0$
#805
b1 /
1$
#810
0$
#815
b10 0
b10 :
b10 C
1%
15
b0 /
1$
#820
0$
#825
b1 /
1$
#830
0$
#835
b1 E
b1 <
b1 2
b1 A
b1 @
b1 8
b1 7
b1 -
b1 ,
0%
05
b0 /
1$
#840
0$
#845
b1 /
1$
#850
0$
#855
1%
15
b0 /
1$
#860
0$
#865
b1 /
1$
#870
0$
#875
b10 2
b10 <
b10 E
b10 -
b10 ,
b10 8
b10 7
b10 A
b10 @
0%
05
b0 /
1$
#880
0$
#885
b1 /
1$
#890
0$
#895
1%
15
b0 /
1$
#900
0$
#905
b1 /
1$
#910
0$
#915
b11 E
b11 <
b11 2
b11 A
b11 @
b11 8
b11 7
b11 -
b11 ,
0%
05
b0 /
1$
#920
0$
#925
b1 /
1$
#930
0$
#935
1%
15
b0 /
1$
#940
0$
#945
b1 /
1$
#950
0$
#955
b100 2
b100 <
b100 E
b100 -
b100 ,
b100 8
b100 7
b100 A
b100 @
0%
05
b0 /
1$
#960
0$
#965
b1 /
1$
#970
0$
#975
1%
15
b0 /
1$
#980
0$
#985
b1 /
1$
#990
0$
#995
b101 E
b101 <
b101 2
b101 A
b101 @
1(
b101 8
b101 7
1'
b101 -
b101 ,
0%
05
b0 /
1$
#1000
0$
#1005
b1 /
1$
#1010
0$
#1015
b1 G
b1 4
1%
15
b0 /
1$
#1020
0$
#1025
b1 /
1$
#1030
0$
#1035
b110 2
b110 <
b110 E
b110 -
b110 ,
1&
b110 8
b110 7
b110 A
b110 @
0%
05
b0 /
1$
#1040
0$
#1045
b1 /
1$
#1050
0$
#1055
b11 4
b1 >
b11 G
1%
15
b0 /
1$
#1060
0$
#1065
b1 /
1$
#1070
0$
#1075
b111 E
b111 <
b111 2
b111 A
b111 @
b111 8
b111 7
b111 -
b111 ,
0%
05
b0 /
1$
#1080
0$
#1085
b1 /
1$
#1090
0$
#1095
b111 G
b11 >
b111 4
1%
15
b0 /
1$
#1100
0$
#1105
b1 /
1$
#1110
0$
#1115
b1000 2
b1000 <
b1000 E
b1000 -
b1000 ,
0&
b1000 8
b1000 7
0'
b1000 A
b1000 @
0(
0%
05
b0 /
1$
#1120
0$
#1125
b1 /
1$
#1130
0$
#1135
b1110 4
b110 >
b1110 G
1%
15
b0 /
1$
#1140
0$
#1145
b1 /
1$
#1150
0$
#1155
b1001 E
b1001 <
b1001 2
b1001 A
b1001 @
b1001 8
b1001 7
b1001 -
b1001 ,
0%
05
b0 /
1$
#1160
0$
#1165
b1 /
1$
#1170
0$
#1175
b11100 G
b1100 >
b11100 4
1%
15
b0 /
1$
#1180
0$
#1185
b1 /
1$
#1190
0$
#1195
b1010 2
b1010 <
b1010 E
b1010 -
b1010 ,
b1010 8
b1010 7
b1010 A
b1010 @
0%
05
b0 /
1$
#1200
0$
#1205
b1 /
1$
#1210
0$
#1215
b111000 4
b11000 >
b111000 G
1%
15
b0 /
1$
#1220
0$
#1225
b1 /
1$
#1230
0$
#1235
b1011 E
b1011 <
b1011 2
b1011 A
b1011 @
b1011 8
b1011 7
b1011 -
b1011 ,
0%
05
b0 /
1$
#1240
0$
#1245
b1 /
1$
#1250
0$
#1255
b1110000 G
b110000 >
b1110000 4
1%
15
b0 /
1$
#1260
0$
#1265
b1 /
1$
#1270
0$
#1275
b1100 2
b1100 <
b1100 E
b1100 -
b1100 ,
b1100 8
b1100 7
b1100 A
b1100 @
0%
05
b0 /
1$
#1280
0$
#1285
b1 /
1$
#1290
0$
#1295
b11100000 4
b1100000 >
b11100000 G
1%
15
b0 /
1$
#1300
0$
#1305
b1 /
1$
#1310
0$
#1315
b1101 E
b1101 <
b1101 2
b1101 A
b1101 @
b1101 8
b1101 7
b1101 -
b1101 ,
1&
0%
05
b0 /
1$
#1320
0$
#1325
b1 /
1$
#1330
0$
#1335
b111000000 G
b11000001 >
b111000000 4
1%
15
b0 /
1$
#1340
0$
#1345
b1 /
1$
#1350
0$
#1355
b1110 2
b1110 <
b1110 E
b1110 -
b1110 ,
0&
b1110 8
b1110 7
1'
b1110 A
b1110 @
1(
0%
05
b0 /
1$
#1360
0$
#1365
b1 /
1$
#1370
0$
#1375
b1110000001 4
b110000010 >
b1110000001 G
1%
15
b0 /
1$
#1380
0$
#1385
b1 /
1$
#1390
0$
#1395
b11 F
b1111 E
b11 =
b1111 <
b11 3
b1111 2
b1111 A
b1111 @
b1111 8
b1111 7
b1111 -
b1111 ,
0%
05
b0 /
1$
#1400
0$
#1405
b1 /
b11 3
b11 =
b11 F
1$
0*
1+
#1410
0$
#1415
b100 F
b100 =
b100 3
b0 @
b11100000011 G
b11 C
b0 7
b1100000100 >
b11 :
b0 ,
b11100000011 4
b11 0
1%
15
b0 /
1$
#1420
0$
#1425
b1 /
1$
#1430
0$
#1435
0%
05
b0 /
1$
#1440
0$
#1445
b1 /
1$
#1450
0$
#1455
b0 2
b0 <
b0 E
b0 -
b0 8
0'
b0 A
0(
b0 3
1)
b0 =
b0 F
b0 4
b100 0
b0 >
b100 :
b0 G
b100 C
1%
15
b0 /
1$
#1460
0$
#1465
b1 /
1$
#1470
0$
#1475
b1 F
b1 =
b1 3
b0 C
b0 :
b10 6
b0 0
1%
15
b0 /
1$
#1480
0$
#1485
b1 /
1$
#1490
0$
#1495
b10 =
b10 F
b10 3
0)
b1 0
b1 :
b1 C
1%
15
b0 /
1$
#1500
0$
#1505
b1 /
1$
#1510
0$
#1515
0%
05
b0 /
1$
#1520
0$
#1525
b1 /
1$
#1530
0$
#1535
b10 C
b10 :
b10 0
1%
15
b0 /
1$
#1540
0$
#1545
b1 /
1$
#1550
0$
#1555
b1 2
b1 <
b1 E
b1 -
b1 ,
b1 8
b1 7
b1 A
b1 @
0%
05
b0 /
1$
#1560
0$
#1565
b1 /
1$
#1570
0$
#1575
1%
15
b0 /
1$
#1580
0$
#1585
b1 /
1$
#1590
0$
#1595
b10 E
b10 <
b10 2
b10 A
b10 @
b10 8
b10 7
b10 -
b10 ,
0%
05
b0 /
1$
#1600
0$
#1605
b1 /
1$
#1610
0$
#1615
1%
15
b0 /
1$
#1620
0$
#1625
b1 /
1$
#1630
0$
#1635
b11 2
b11 <
b11 E
b11 -
b11 ,
b11 8
b11 7
b11 A
b11 @
0%
05
b0 /
1$
#1640
0$
#1645
b1 /
1$
#1650
0$
#1655
1%
15
b0 /
1$
#1660
0$
#1665
b1 /
1$
#1670
0$
#1675
b100 E
b100 <
b100 2
b100 A
b100 @
b100 8
b100 7
b100 -
b100 ,
0%
05
b0 /
1$
#1680
0$
#1685
b1 /
1$
#1690
0$
#1695
1%
15
b0 /
1$
#1700
0$
#1705
b1 /
1$
#1710
0$
#1715
b101 2
b101 <
b101 E
b101 -
b101 ,
b101 8
b101 7
1'
b101 A
b101 @
1(
0%
05
b0 /
1$
#1720
0$
#1725
b1 /
1$
#1730
0$
#1735
b1 4
b1 G
1%
15
b0 /
1$
#1740
0$
#1745
b1 /
1$
#1750
0$
#1755
b110 E
b110 <
b110 2
b110 A
b110 @
b110 8
b110 7
b110 -
b110 ,
1&
0%
05
b0 /
1$
#1760
0$
#1765
b1 /
1$
#1770
0$
#1775
b11 G
b1 >
b11 4
1%
15
b0 /
1$
#1780
0$
#1785
b1 /
1$
#1790
0$
#1795
b111 2
b111 <
b111 E
b111 -
b111 ,
b111 8
b111 7
b111 A
b111 @
0%
05
b0 /
1$
#1800
0$
#1805
b1 /
1$
#1810
0$
#1815
b111 4
b11 >
b111 G
1%
15
b0 /
1$
#1820
0$
#1825
b1 /
1$
#1830
0$
#1835
b1000 E
b1000 <
b1000 2
b1000 A
b1000 @
0(
b1000 8
b1000 7
0'
b1000 -
b1000 ,
0&
0%
05
b0 /
1$
#1840
0$
#1845
b1 /
1$
#1850
0$
#1855
b1110 G
b110 >
b1110 4
1%
15
b0 /
1$
#1860
0$
#1865
b1 /
1$
#1870
0$
#1875
b1001 2
b1001 <
b1001 E
b1001 -
b1001 ,
b1001 8
b1001 7
b1001 A
b1001 @
0%
05
b0 /
1$
#1880
0$
#1885
b1 /
1$
#1890
0$
#1895
b11100 4
b1100 >
b11100 G
1%
15
b0 /
1$
#1900
0$
#1905
b1 /
1$
#1910
0$
#1915
b1010 E
b1010 <
b1010 2
b1010 A
b1010 @
b1010 8
b1010 7
b1010 -
b1010 ,
0%
05
b0 /
1$
#1920
0$
#1925
b1 /
1$
#1930
0$
#1935
b111000 G
b11000 >
b111000 4
1%
15
b0 /
1$
#1940
0$
#1945
b1 /
1$
#1950
0$
#1955
b1011 2
b1011 <
b1011 E
b1011 -
b1011 ,
b1011 8
b1011 7
b1011 A
b1011 @
0%
05
b0 /
1$
#1960
0$
#1965
b1 /
1$
#1970
0$
#1975
b1110000 4
b110000 >
b1110000 G
1%
15
b0 /
1$
